{
  "type": "Feature",
  "geometry": {
    "type": "Point",
    "coordinates": [
      -123.75861111111111,
      44.37722222222222
    ]
  },
  "properties": {
    "FacilityLongitude": -123.75861111111111,
    "FacilityDescription": "<h2>Overview</h2>River Edge is a group campground nestled on the banks of the Alsea River, surrounded by large Sitka spruce, Douglas fir, alder trees and blackberries. Groups of families and friends enjoy the area for its great fishing opportunities, as well as its scenic beauty.<h4>Natural Features:</h4>River Edge is located in the eastern part of the Siuslaw National Forest, which encompasses over 630,000 acres as it stretches from the lush forests of the coastal mountains to the Oregon Dunes and Pacific Coast.<br /><br />The Alsea River flows 48.5 miles from the town of Alsea out to the Pacific Coast at Waldport and Alsea Bay.<h4>Recreation:</h4>The campgrounds open play field is ideal for games like Frisbee and soccer, so campers are encouraged to bring sports equipment to make use of the space. The river beckons visitors for canoeing and swimming. Anglers cast for Coho and Chinook salmon and Steelhead trout.<h4>Facilities:</h4>The accessible group campground accommodates 100 guests. A large shelter covers several picnic tables. A campfire ring and grills are located under the shelter, and an additional campfire ring is outside the shelter. Drinking water, electricity and four vault toilets are provided. <br /><br />Firewood may be purchased onsite.<h4>Nearby Attractions:</h4>Sandy beaches stretch north and south of Waldport, about 25 minutes from the campground. Beautiful Cape Perpetua Scenic Area, where whale watching is a popular activity, is another 15 minutes south of Waldport.<br /><br />Marys Peak is the highest point in Oregons Coast Range and has been designated a Scenic Botanical Area because of its rich, unique scenery and plants.<br /><br />The Rock Creek Wilderness Area, within the Siuslaw National Forest off Coastal Highway 101, encompasses about 7,500 acres. The area is comprised of a dense coniferous rainforest, where bigleaf maple and red alder trees line the creeks, and rhododendrons dot the forest floor.",
    "FacilityLatitude": 44.37722222222222,
    "FacilityTypeDescription": "Camping",
    "FacilityPhone": "541-547-3679",
    "FacilityDirections": "From Waldport, head east on Highway 34 for about 26 miles and look for campground signs on the right.",
    "FacilityName": "RIVER EDGE",
    "LastUpdatedDate": "2015-03-12 02:32:49",
    "FacilityADAAccess": true,
    "LegacyFacilityID": 73832,
    "OrgFacilityID": "AN373832",
    "FacilityID": 233903,
    "campsites": [
      {
        "LastUpdatedDate": "2015-03-05 04:21:21",
        "TypeOfUse": "Overnight",
        "CreatedDate": "2014-05-02 18:25:50",
        "CampsiteType": "GROUP STANDARD NONELECTRIC",
        "CampsiteID": 86939,
        "CampsiteName": "GROUP",
        "Loop": "AREA RIVER EDGE",
        "CampsiteAccessible": true,
        "FacilityID": 233903,
        "attributes": [
          {
            "AttributeValue": "2:00 PM",
            "AttributeName": "Checkin Time"
          },
          {
            "AttributeValue": "1:00 PM",
            "AttributeName": "Checkout Time"
          },
          {
            "AttributeValue": "Pull-Through",
            "AttributeName": "Driveway Entry"
          },
          {
            "AttributeValue": "Paved",
            "AttributeName": "Driveway Surface"
          },
          {
            "AttributeValue": 100,
            "AttributeName": "Max Num of People"
          },
          {
            "AttributeValue": 16,
            "AttributeName": "Max Num of Vehicles"
          },
          {
            "AttributeValue": 1,
            "AttributeName": "Min Num of People"
          },
          {
            "AttributeValue": "Partial",
            "AttributeName": "Shade"
          },
          {
            "AttributeValue": "Site-Specific",
            "AttributeName": "Site Reserve Type"
          },
          {
            "AttributeValue": "Single",
            "AttributeName": "Capacity/Size Rating"
          }
        ]
      }
    ],
    "address": {
      "FacilityAddressID": 8031924,
      "PostalCode": 97324,
      "AddressStateCode": "OR",
      "FacilityStreetAddress1": "23116 E. ALSEA HWY",
      "City": "ALSEA",
      "FacilityID": 233903,
      "AddressCountryCode": "USA"
    }
  }
}