{
  "type": "Feature",
  "geometry": {
    "type": "Point",
    "coordinates": [
      -86.68527777777778,
      46.486666666666665
    ]
  },
  "properties": {
    "FacilityLongitude": -86.68527777777778,
    "FacilityDescription": "<h2>Overview</h2>Juniper Flats Group Campground is one of only a few places to stay on beautiful Grand Island. The islands scenic natural beauty and interesting history make it a popular place for camping and other outdoor activities.<br /> <br />The Grand Island National Recreation Area boasts massive 300-foot wave-cut sandstone cliffs, 13,500 acres of lush forest, beaches of fine sand, winter ice caves and historic buildings and artifacts dating back as far as 2000 B.C. <h4>Natural Features:</h4>Juniper Flats Group Campground is located on the west side of Grand Island near the Waterfall and Mather beaches. <br /> <br />The area is heavily forested and primarily shady throughout the day. The campground is situated away from the beach, but the lake is visible from the site.<h4>Recreation:</h4>The island offers more than 30 miles of hiking and mountain biking trails, complete with spectacular scenery. Visitors also enjoy fishing on the island. Anglers will find plentiful salmon, trout, perch, pike, walleye and bass. A variety of wildlife also make its home on the island.<br /> <br />Kayaking, canoeing and boating are also popular pastimes. Boats, however, must be anchored offshore because of the rocky lake bottom and heavy surf.<h4>Facilities:</h4>The campground provides one large group tent campsite, equipped with tables and a campfire circle. Vault toilets and drinking water are provided. Bear poles and bear boxes are available for food storage. <br /> <br />",
    "FacilityLatitude": 46.486666666666665,
    "FacilityTypeDescription": "Camping",
    "FacilityDirections": "Visitors can get to the island via passenger ferry or private watercraft. The ferry departs from Grand Island Landing on the mainland, located on State Route 28. Look for the Grand Island National Recreation Area signs. Prices and schedules vary from season to season. For information or reservations, call 906-387-3503 or <a href=http://www.grandislandmi.com target=_blank>click here</a>.<br /> <br />Juniper Flats is located approximately 4 miles from where the ferry boat docks at Williams Landing. Visitors must hike or bike from the landing to Juniper Flats. Private vehicles and off-road vehicles are not allowed on the island. The campground is also accessible by kayaking to Waterfall Beach and walking 1,000 feet to the site.",
    "FacilityName": "JUNIPER FLATS GROUP CAMPSITE on GRAND ISLAND",
    "LastUpdatedDate": "2015-03-12 02:44:41",
    "LegacyFacilityID": 93118,
    "OrgFacilityID": "AN393118",
    "FacilityID": 234658,
    "campsites": [
      {
        "LastUpdatedDate": "2015-03-05 04:51:11",
        "TypeOfUse": "Overnight",
        "CreatedDate": "2014-05-02 18:19:21",
        "CampsiteType": "GROUP TENT ONLY AREA NONELECTRIC",
        "CampsiteID": 78586,
        "CampsiteName": "Juniper Flats",
        "Loop": "JUNIPER FLATS GROUP CAMPSITE on GRAND ISLAND",
        "CampsiteAccessible": false,
        "FacilityID": 234658,
        "attributes": [
          {
            "AttributeValue": "12:00 PM",
            "AttributeName": "Checkout Time"
          },
          {
            "AttributeValue": "Good",
            "AttributeName": "Condition Rating"
          },
          {
            "AttributeValue": 21120,
            "AttributeName": "Hike In Distance to Site"
          },
          {
            "AttributeValue": "Good",
            "AttributeName": "Location Rating"
          },
          {
            "AttributeValue": 25,
            "AttributeName": "Max Num of People"
          },
          {
            "AttributeValue": 7,
            "AttributeName": "Min Num of People"
          },
          {
            "AttributeValue": "Domestic",
            "AttributeName": "Pets Allowed"
          },
          {
            "AttributeValue": "Partial",
            "AttributeName": "Shade"
          },
          {
            "AttributeValue": "Hike-In",
            "AttributeName": "Site Access"
          },
          {
            "AttributeValue": "Site-Specific",
            "AttributeName": "Site Reserve Type"
          },
          {
            "AttributeValue": "12:00 PM",
            "AttributeName": "Checkin Time"
          }
        ]
      }
    ],
    "address": {
      "FacilityAddressID": 8032697,
      "PostalCode": 49862,
      "AddressStateCode": "MI",
      "FacilityStreetAddress1": "400 E Munising Ave",
      "City": "Munising",
      "FacilityID": 234658,
      "AddressCountryCode": "USA"
    }
  }
}