{
  "type": "Feature",
  "geometry": {
    "type": "Point",
    "coordinates": [
      -82.81638888888888,
      34.38111111111111
    ]
  },
  "properties": {
    "FacilityLongitude": -82.81638888888888,
    "FacilityDescription": "<h2>Overview</h2>Crescent Group Campground is located along the shores of Hartwell Lake in South Carolina. <br /><br />Spanning parts of South Carolina and Georgia, Hartwell Lake is one of the largest and most visited public recreation lakes in the Southeast. It comprises nearly 56,000 acres of water and has a shoreline of 962 miles.<h4>Natural Features:</h4>The lake shore is thickly forested with mostly pine, and the lake itself is large with many inlets and coves to explore. <br /><br />Numerous species of birds call this area home, including waterfowl, shorebirds, woodland birds and even the occasional peregrine falcon and bald eagle.<h4>Recreation:</h4>Fishing is one of the most popular activities at the lake. Sought-after species include largemouth bass, bream, crappie, catfish, striped bass and hybrid bass. <br /><br />The lake appeals to boaters of all kinds, whether their specialty is canoeing, sailing or motor boating. Coves and areas of quiet water provide water skiers with excellent surfaces.<br /><br />Swimmers will find sand beaches and designated swim areas along the shoreline. <h4>Facilities:</h4>Crescent offers two group camp areas, which are ideal for family gatherings and functions. Sites are lakefront with water and 50-amp electrical hookups. Each loop contains a large centrally located pavilion with lights and grills that can accommodate more than 100 people.<h4>Nearby Attractions:</h4>The campground is a short drive away from Clemson, South Carolina and Clemson University, offering additional tourism opportunities, along with grocery stores, gas stations and restaurants.",
    "FacilityLatitude": 34.38111111111111,
    "FacilityTypeDescription": "Camping",
    "FacilityPhone": "888-893-0678",
    "FacilityDirections": "From Hartwell, Georgia, take Highway 29 east for approximately 8 miles. Turn left onto Ginn Road. Take the first left onto Campers Way and continue straight to the campground.",
    "FacilityName": "CRESCENT",
    "LastUpdatedDate": "2015-03-12 02:11:45",
    "LegacyFacilityID": 71114,
    "OrgFacilityID": "AN371114",
    "FacilityID": 232561,
    "campsites": [
      {
        "LastUpdatedDate": "2015-03-12 03:40:46",
        "TypeOfUse": "Overnight",
        "CreatedDate": "2014-05-02 17:32:27",
        "CampsiteType": "GROUP STANDARD ELECTRIC",
        "CampsiteID": 21732,
        "CampsiteName": "LOOP A Sites 1-10",
        "Loop": "CRESCENT",
        "CampsiteAccessible": false,
        "FacilityID": 232561
      },
      {
        "LastUpdatedDate": "2015-03-12 03:40:46",
        "TypeOfUse": "Overnight",
        "CreatedDate": "2014-05-02 17:32:27",
        "CampsiteType": "GROUP STANDARD ELECTRIC",
        "CampsiteID": 21733,
        "CampsiteName": "LOOP B Sites 1-22",
        "Loop": "CRESCENT",
        "CampsiteAccessible": false,
        "FacilityID": 232561
      }
    ],
    "address": {
      "FacilityAddressID": 8030579,
      "PostalCode": 29684,
      "AddressStateCode": "SC",
      "FacilityStreetAddress1": "150 Campers Way",
      "City": "Starr",
      "FacilityID": 232561,
      "AddressCountryCode": "USA"
    }
  }
}