{
  "type": "Feature",
  "geometry": {
    "type": "Point",
    "coordinates": [
      -116.88027777777778,
      34.23527777777778
    ]
  },
  "properties": {
    "FacilityLongitude": -116.88027777777778,
    "FacilityDescription": "<h2>Overview</h2>Buttercup Group Camp is an outdoor oasis nestled in Southern Californias pine-covered mountains. Big Bear Lake is nearby, a popular destination for a variety of recreational activities. The campground offers a great escape from city life and it is one of the best locales for group camping.<h4>Natural Features:</h4>The group campground is situated at an elevation of about 7,000 feet and is heavily forested with pine trees. The site is relatively shady and secluded. It is about two miles from Big Bear Lake and is accessed by a dirt road.<h4>Recreation:</h4>Fishing and boating at Big Bear Lake are popular activities. Anglers can look forward to trout, bluegill, crappie, catfish and largemouth bass, among other species. Because of the very cold water and the presence of underwater obstacles near the shoreline, swimming at the lake is sometimes discouraged.<br /><br />Visitors also enjoy the areas plentiful hiking, mountain biking and climbing opportunities. The campground provides access to a number of trails and points of exploration.<h4>Facilities:</h4>The group campground offers one large, accessible site that can accommodate up to 40 people and eight vehicles for tent or RV camping. The site is equipped with tables, grills and a campfire circle. Vault toilets and drinking water are provided.<h4>Nearby Attractions:</h4>A general store and restaurants can be found in the city of Big Bear Lake.",
    "FacilityLatitude": 34.23527777777778,
    "FacilityTypeDescription": "Camping",
    "FacilityPhone": "909-866-8550",
    "FacilityDirections": "From San Bernardino, take I-10 east to Running Springs. Turn onto State Highway 18 and continue to Big Bear Lake Dam. Continue about 6 miles on State Highway 18 and turn right on Summit Boulevard. Turn left at the end of road and go about a half-mile to the second gate on the right.",
    "FacilityName": "BUTTERCUP GROUP CAMP",
    "LastUpdatedDate": "2015-03-12 02:02:13",
    "FacilityADAAccess": true,
    "LegacyFacilityID": 70171,
    "OrgFacilityID": "AN370171",
    "FacilityID": 231967,
    "campsites": [
      {
        "LastUpdatedDate": "2015-03-12 04:51:59",
        "TypeOfUse": "Overnight",
        "CreatedDate": "2014-05-02 18:13:33",
        "CampsiteType": "GROUP STANDARD NONELECTRIC",
        "CampsiteID": 71181,
        "CampsiteName": 1,
        "Loop": "BUTT",
        "CampsiteAccessible": true,
        "FacilityID": 231967,
        "attributes": [
          {
            "AttributeValue": "Y",
            "AttributeName": "Campfire Allowed"
          },
          {
            "AttributeValue": "Single",
            "AttributeName": "Capacity/Size Rating"
          },
          {
            "AttributeValue": "2:00 PM",
            "AttributeName": "Checkin Time"
          },
          {
            "AttributeValue": "12:00 PM",
            "AttributeName": "Checkout Time"
          },
          {
            "AttributeValue": "Gravel",
            "AttributeName": "Driveway Surface"
          },
          {
            "AttributeValue": "Y",
            "AttributeName": "Fire Pit"
          },
          {
            "AttributeValue": 40,
            "AttributeName": "Max Num of People"
          },
          {
            "AttributeValue": 8,
            "AttributeName": "Max Num of Vehicles"
          },
          {
            "AttributeValue": 1,
            "AttributeName": "Min Num of People"
          },
          {
            "AttributeValue": "Domestic",
            "AttributeName": "Pets Allowed"
          },
          {
            "AttributeValue": "Y",
            "AttributeName": "Picnic Table"
          },
          {
            "AttributeValue": "Y",
            "AttributeName": "Privacy"
          },
          {
            "AttributeValue": "Y",
            "AttributeName": "Quiet Area"
          },
          {
            "AttributeValue": "Full",
            "AttributeName": "Shade"
          },
          {
            "AttributeValue": "Site-Specific",
            "AttributeName": "Site Reserve Type"
          },
          {
            "AttributeValue": "Y",
            "AttributeName": "Water Hookup"
          },
          {
            "AttributeValue": "Y",
            "AttributeName": "BBQ"
          }
        ]
      }
    ],
    "address": {
      "FacilityAddressID": 8029985,
      "AddressStateCode": "CA",
      "FacilityStreetAddress1": "SAN BERNARDINO",
      "FacilityID": 231967,
      "AddressCountryCode": "USA"
    }
  }
}