{
  "type": "Feature",
  "geometry": {
    "type": "Point",
    "coordinates": [
      -119.115,
      37.269444444444446
    ]
  },
  "properties": {
    "FacilityLongitude": -119.115,
    "FacilityDescription": "<h2>Overview</h2>Badger Flats Group Camp sits in a quiet and isolated area along Rancheria Creek, at an elevation of over 8,000 feet in the High Sierra.  The site sits on open and flat land shaded by fir trees and can accommodate up to 100 people and 35 vehicles. <h4>Natural Features:</h4>The Sierra National Forest, located on the western slope of the central Sierra Nevada, is known for its spectacular mountain scenery and abundant natural resources.<br /><br />The terrain includes rolling, oak-covered foothills, heavily forested middle elevation slopes and the starkly beautiful alpine landscape of the High Sierra.<h4>Recreation:</h4>There is trailhead access to the Kaiser Wilderness. There is also a trail that connects to the California Riding and Hiking Trail.<br /><br /> There is a sandy area along Rancheria Creek, and wading is possible.  <h4>Facilities:</h4>Horses are permitted in this camp, but no equestrian amenities are provided. Each unit has a grill, fire ring, bear-proof food locker and picnic table.<br /><br />Vault toilets are provided. Drinking water is not available at this campground.<h4>Nearby Attractions:</h4>Huntington Lake is about 5 miles away and offers many recreational activities, including hiking, horseback riding, biking, canoeing, sailing, fishing, windsurfing and swimming. Anglers can fish for rainbow trout, brown trout or kokanne salmon.",
    "FacilityLatitude": 37.269444444444446,
    "FacilityTypeDescription": "Camping",
    "FacilityPhone": "559-893-2111",
    "FacilityDirections": "Take Hwy 168 east from Clovis to Shaver Lake. Continue through Shaver Lake to Huntington Lake. At the east end of Huntington Lake, turn right onto Kaiser Pass Road (at Eastwood Visitor Center). Travel 5 miles up the Kaiser Pass Road to Badger Group Campground.",
    "FacilityName": "BADGER FLATS GROUP",
    "LastUpdatedDate": "2015-03-12 02:15:42",
    "LegacyFacilityID": 71586,
    "OrgFacilityID": "AN371586",
    "FacilityID": 232808,
    "campsites": [
      {
        "LastUpdatedDate": "2015-03-05 04:41:14",
        "TypeOfUse": "Overnight",
        "CreatedDate": "2014-05-02 18:07:09",
        "CampsiteType": "GROUP STANDARD NONELECTRIC",
        "CampsiteID": 63625,
        "CampsiteName": 1,
        "Loop": "AREA BADGER FLATS",
        "CampsiteAccessible": false,
        "FacilityID": 232808,
        "attributes": [
          {
            "AttributeValue": "Single",
            "AttributeName": "Capacity/Size Rating"
          },
          {
            "AttributeValue": "2:00 PM",
            "AttributeName": "Checkin Time"
          },
          {
            "AttributeValue": "12:00 PM",
            "AttributeName": "Checkout Time"
          },
          {
            "AttributeValue": "Pull-Through",
            "AttributeName": "Driveway Entry"
          },
          {
            "AttributeValue": "Gravel",
            "AttributeName": "Driveway Surface"
          },
          {
            "AttributeValue": "Y",
            "AttributeName": "Fire Pit"
          },
          {
            "AttributeValue": 100,
            "AttributeName": "Max Num of People"
          },
          {
            "AttributeValue": 35,
            "AttributeName": "Max Num of Vehicles"
          },
          {
            "AttributeValue": 1,
            "AttributeName": "Min Num of People"
          },
          {
            "AttributeValue": "Domestic",
            "AttributeName": "Pets Allowed"
          },
          {
            "AttributeValue": "Y",
            "AttributeName": "Picnic Table"
          },
          {
            "AttributeValue": "Full",
            "AttributeName": "Shade"
          },
          {
            "AttributeValue": "Site-Specific",
            "AttributeName": "Site Reserve Type"
          },
          {
            "AttributeValue": "Y",
            "AttributeName": "Campfire Allowed"
          }
        ]
      }
    ],
    "address": {
      "FacilityAddressID": 8030819,
      "AddressStateCode": "CA",
      "FacilityID": 232808,
      "AddressCountryCode": "USA"
    }
  }
}