{
  "type": "Feature",
  "geometry": {
    "type": "Point",
    "coordinates": [
      -122.65333333333334,
      39.35722222222223
    ]
  },
  "properties": {
    "FacilityLongitude": -122.65333333333334,
    "FacilityDescription": "<h2>Overview</h2>Perched 1,700 feet above sea level in the lush expanse of the Mendocino National Forest, the Gray Pine Group Camp is a beautiful recreation oasis for large groups and parties.<h4>Natural Features:</h4>The Mendocino National Forest, Californias only national forest that is not crossed by a paved road, straddles the eastern spur of the Coastal Mountain Range in northwestern California, just a three-hour drive north of San Francisco and Sacramento. <br /><br />Sprinkled throughout the dense green forest are several lakes, offering visitors additional recreational opportunities against a stunning backdrop.<h4>Recreation:</h4>Mendocino National Forests 913,306 acres of mountains and canyons offer a variety of recreational opportunities, including horseback riding, hiking, backpacking, boating, fishing and hunting, nature study and off-highway vehicle riding.<br /><br />Whether its deer, birds, rabbits, chipmunks or perhaps the occasional bear, wildlife viewing is always a popular activity for visitors. The area is also an extremely popular destination during hunting season. <h4>Facilities:</h4>Gray Pine Group Camp offers traditional primitive camping and can hold up to 75 guests comfortably. <h4>Nearby Attractions:</h4>Popular OHV riding trails are easily accessible from the campground.",
    "FacilityLatitude": 39.35722222222223,
    "FacilityTypeDescription": "Camping",
    "FacilityPhone": "530-963-3128",
    "FacilityDirections": "From the South: From Interstate 5 take Exit 586 for Maxwell Road. Travel west for approximately nine miles to the town of Sites. At the junction turn right turn onto Sites-Ladoga Road and travel for about 15 miles to the town of Lodoga. Turn right at the junction, cross the bridge onto Ladoga-Stonyford Road and travel for approximately eight miles to the town of Stonyford. Turn left at the stop sign, drive two blocks north to Fouts Springs Road and turn left. Travel on Fouts Springs Road/Forest Road M10 for nine miles. Turn right onto Forest Road 18N03 towards Davis Flat and drive approximately 1/2 mile. Turn right at the locked gate; this is the entrance to Gray Pine.<br /><br />From the North: From Interstate 5 take 162 West from Willows and travel 23 miles. At the junction turn left onto County Road 306/Stonyford-Elk Creek Road and travel about 18 miles to the town of Stonyford. Turn right onto Fouts Springs Road/Forest Road M10. After about nine miles turn right onto Forest Road 18N03 towards Davis Flat and drive approximately 1/2 mile. Turn right at the locked gate; this is the entrance to Gray Pine.",
    "FacilityName": "GRAY PINE GROUP CAMPGROUND",
    "LastUpdatedDate": "2015-03-12 02:21:11",
    "LegacyFacilityID": 72052,
    "OrgFacilityID": "AN372052",
    "FacilityID": 233162,
    "campsites": [
      {
        "LastUpdatedDate": "2015-03-05 04:24:29",
        "TypeOfUse": "Overnight",
        "CreatedDate": "2014-05-02 18:21:48",
        "CampsiteType": "GROUP STANDARD NONELECTRIC",
        "CampsiteID": 81045,
        "CampsiteName": "G1",
        "Loop": "GRAY PINE GROUP CAMPGROUND",
        "CampsiteAccessible": false,
        "FacilityID": 233162,
        "attributes": [
          {
            "AttributeValue": "11:00 AM",
            "AttributeName": "Checkout Time"
          },
          {
            "AttributeValue": "Y",
            "AttributeName": "Double Driveway"
          },
          {
            "AttributeValue": "Gravel",
            "AttributeName": "Driveway Surface"
          },
          {
            "AttributeValue": 75,
            "AttributeName": "Max Num of People"
          },
          {
            "AttributeValue": 25,
            "AttributeName": "Max Num of Vehicles"
          },
          {
            "AttributeValue": "Partial",
            "AttributeName": "Shade"
          },
          {
            "AttributeValue": "Site-Specific",
            "AttributeName": "Site Reserve Type"
          },
          {
            "AttributeValue": "2:00 PM",
            "AttributeName": "Checkin Time"
          }
        ]
      }
    ],
    "address": {
      "FacilityAddressID": 8031173,
      "PostalCode": "95979-0160",
      "AddressStateCode": "CA",
      "FacilityStreetAddress1": "Stonyford Work Station, P.O. Box 160",
      "City": "Stonyford",
      "FacilityID": 233162,
      "AddressCountryCode": "USA"
    }
  }
}