{
  "type": "Feature",
  "geometry": {
    "type": "Point",
    "coordinates": [
      -122.91694444444445,
      40.233333333333334
    ]
  },
  "properties": {
    "FacilityLongitude": -122.91694444444445,
    "FacilityDescription": "<h2>Overview</h2>Post Creek Guard Station was built in 1934 by the Civilian Conservation Corps for use as a wildfire lookout. It is now available for recreational use. This historic station is eligible for inclusion to the National Register of Historic Places.<br /><br />Guests can drive to Post Creek Guard Station, although the last 10 miles of the trip are on gravel roads. This charming cabin offers some amenities, but guests will have to bring supplies and gear. Post Creek Guard Station offers the chance to relish the peace and quiet in a beautiful, secluded location. <h4>Natural Features:</h4>The guard station is located in the Hayfork Area of Shasta-Trinity National Park on a ridgeline above Beegum Gorge. Beegum Creek, which is just to the north of thecabin, is a major waterway in this area. The Yolla Bolla Mountains and Yolla Bolly-Middle Eel Wilderness are to the south.   <h4>Recreation:</h4>Post Creek Guard Station is an ideal location to relax and enjoy the view. Guests who want to do something a bit more active can find hiking and other recreational activities nearby. On hot days guests can take a dip in the swimming hole at Post Creek, located a quarter mile from the guard station. <h4>Facilities:</h4>This 19x30 cabin accommodates up to eight people and has two rooms. The kitchen is equipped with a table and chairs. Furnishings include two beds with mattresses and a couch. There is an indoor flush toilet. Cold running water is available inside the cabin, but it is unsafe for drinking. A fire pit and picnic table are located outside.<br /><br />The cabin does not have electricity, heat, a stove or refrigerator. Guests should bring their own potable water for drinking, cooking and washing. Visitors should plan on bringing bedding, cookware, dishes, utensils and trash bags to pack out garbage. The use of portable stoves using gas, jellied petroleum or pressurized liquid fuel is allowed with a valid California campfire permit.<h4>Nearby Attractions:</h4>Guests may wish to explore the Yolla Bolly-Middle Eel Wilderness or paddle in the whitewater at Beegum Creek.",
    "FacilityLatitude": 40.233333333333334,
    "FacilityTypeDescription": "Camping",
    "FacilityDirections": "Turn left off California State Highway 36 onto Forest Road 45 (29N45). Continue to theintersection with Forest Road 28N36. Turn right on 28N36 and follow untilyou see the green gate on the right. Turn right at the green gate whichstates &quot;Road Closed.&quot;  Open gate, and drive through to the cabin.",
    "FacilityName": "POST CREEK GUARD STATION",
    "LastUpdatedDate": "2015-03-12 02:40:44",
    "LegacyFacilityID": 75269,
    "OrgFacilityID": "AN375269",
    "FacilityID": 234404,
    "campsites": [
      {
        "LastUpdatedDate": "2015-03-12 04:48:35",
        "TypeOfUse": "Overnight",
        "CreatedDate": "2014-05-02 18:11:07",
        "CampsiteType": "CABIN NONELECTRIC",
        "CampsiteID": 68237,
        "CampsiteName": 1,
        "Loop": "AREA POST CREEK GUARD STATION",
        "CampsiteAccessible": false,
        "FacilityID": 234404,
        "attributes": [
          {
            "AttributeValue": "2:00 PM",
            "AttributeName": "Checkin Time"
          },
          {
            "AttributeValue": "11:00 AM",
            "AttributeName": "Checkout Time"
          },
          {
            "AttributeValue": "Back-In",
            "AttributeName": "Driveway Entry"
          },
          {
            "AttributeValue": 6,
            "AttributeName": "Max Num of People"
          },
          {
            "AttributeValue": 2,
            "AttributeName": "Max Num of Vehicles"
          },
          {
            "AttributeValue": 1,
            "AttributeName": "Min Num of People"
          },
          {
            "AttributeValue": "Site-Specific",
            "AttributeName": "Site Reserve Type"
          },
          {
            "AttributeValue": "Y",
            "AttributeName": "Cabin Heating"
          }
        ]
      }
    ],
    "address": {
      "FacilityAddressID": 8032433,
      "PostalCode": 96076,
      "AddressStateCode": "CA",
      "City": "PLATINA",
      "FacilityID": 234404,
      "AddressCountryCode": "USA"
    }
  }
}