{
  "type": "Feature",
  "geometry": {
    "type": "Point",
    "coordinates": [
      -110.42277777777778,
      43.21555555555556
    ]
  },
  "properties": {
    "FacilityLongitude": -110.42277777777778,
    "FacilityDescription": "<h2>Overview</h2>Hoback Guard Station, about 34 miles from Jackson, Wyoming, beckons guests who want a scenic backcountry experience with the convenience of electricity and running water. <h4>Natural Features:</h4>Willows and pines provide sparse shade, and grasses and summer wildflowers are abundant. A creek runs alongside the guard station, which sits at an elevation of 6,600 feet. <h4>Recreation:</h4>Hiking, biking and horseback riding trails crisscross the surrounding mountains, leading visitors to impressive scenery like Cliff Creek Falls. Nearby Sandy Marshall Creek offers great fishing for brown trout, channel catfish, smallmouth bass and occasional tiger trout. <br /><br />Snake River Canyon begins just 15 miles west, with excellent rafting, kayaking, fishing and scenery.<h4>Facilities:</h4>The log cabin has electricity and can accommodate six guests. A campfire ring with grill is located outside. Drinking water, a flush toilet and shower are available Memorial Day to Labor Day. The kitchen is equipped with an electric stove, a variety of cookware, a table with four chairs, a refrigerator and a sink. The bedroom has three bunkbeds with mattresses and a dresser. A phone is also provided. <br /><br />No linens or bedding are included. Guests should bring food, bedding or sleeping bags, towels, soap and garbage bags. <br /><br />Pets and livestock are allowed at the guard station. Livestock may be kept in the corral behind the bunkhouse. <h4>Nearby Attractions:</h4>Popular Jackson, Wyoming is 20 miles away, with restaurants, groceries, galleries, and ski resorts with both winter and summer activities. Grand Teton National Park is just beyond Jackson, with hiking, fishing, boating, canoeing, kayaking and breathtaking scenery.",
    "FacilityLatitude": 43.21555555555556,
    "FacilityTypeDescription": "Camping",
    "FacilityDirections": "From Big Piney, follow U.S. Highway 189 north for 26 miles to the junction of U.S. 189 and 191. Turn left and continue on U.S. 189/191 another 33 miles to Bondurant. The guard station is on the left (west) side of the highway about 1 mile past Bondurant. A key is needed for the locked gate, and should be picked up at the district office prior to arrival.",
    "FacilityName": "HOBACK GUARD STATION",
    "LastUpdatedDate": "2015-03-12 02:43:06",
    "LegacyFacilityID": 75462,
    "OrgFacilityID": "AN375462",
    "FacilityID": 234570,
    "campsites": [
      {
        "LastUpdatedDate": "2015-03-12 04:38:19",
        "TypeOfUse": "Overnight",
        "CreatedDate": "2014-05-02 18:01:31",
        "CampsiteType": "CABIN ELECTRIC",
        "CampsiteID": 56190,
        "CampsiteName": 1,
        "Loop": "HOGS",
        "CampsiteAccessible": false,
        "FacilityID": 234570,
        "attributes": [
          {
            "AttributeValue": "12:00 PM",
            "AttributeName": "Checkin Time"
          },
          {
            "AttributeValue": "12:00 PM",
            "AttributeName": "Checkout Time"
          },
          {
            "AttributeValue": "Pull-Through",
            "AttributeName": "Driveway Entry"
          },
          {
            "AttributeValue": "Gravel",
            "AttributeName": "Driveway Surface"
          },
          {
            "AttributeValue": 6,
            "AttributeName": "Max Num of People"
          },
          {
            "AttributeValue": 4,
            "AttributeName": "Max Num of Vehicles"
          },
          {
            "AttributeValue": 1,
            "AttributeName": "Min Num of People"
          },
          {
            "AttributeValue": 6,
            "AttributeName": "Num of Beds"
          },
          {
            "AttributeValue": "Full",
            "AttributeName": "Shade"
          },
          {
            "AttributeValue": "Site-Specific",
            "AttributeName": "Site Reserve Type"
          },
          {
            "AttributeValue": "Bunk",
            "AttributeName": "Bed Type"
          }
        ]
      }
    ],
    "address": {
      "FacilityAddressID": 8032598,
      "PostalCode": 83113,
      "AddressStateCode": "WY",
      "FacilityStreetAddress1": "14393 S. Hwy 191",
      "City": "BIG PINEY",
      "FacilityID": 234570,
      "AddressCountryCode": "USA"
    }
  }
}