{
  "type": "Feature",
  "geometry": {
    "type": "Point",
    "coordinates": [
      -110.81638888888888,
      42.638333333333335
    ]
  },
  "properties": {
    "FacilityLongitude": -110.81638888888888,
    "FacilityDescription": "<h2>Overview</h2>Cottonwood Group Picnic Site is located next to scenic Cottonwood Lake on the Salt River Mountains, surrounded by the forests of western Wyoming.<h4>Natural Features:</h4>The picnic site is located above Cottonwood Lake, near the peaceful North Fork Creek. A forest of pines and aspens offers shade, and vibrant summer wildflowers are abundant.<br /><br />The Bridger-Teton National Forest offers more than 3.4 million acres of public land for outdoor recreation. With its pristine watersheds, abundant wildlife and immense wildlands, the forest comprises a large part of the Greater Yellowstone Ecosystem, the largest intact ecosystem in the lower 48 United States. <h4>Recreation:</h4>The lake offers great canoeing and boating for smaller craft, as well as fishing for brook and cutthroat trout. <br /><br />Hiking, mountain biking, off-road vehicle and horseback riding trails are in the area.<h4>Facilities:</h4>This day-use picnic site can accommodate up to 50 guests and 8-10 vehicles.  Vault toilets and drinking water are provided. <br /><br />A group overnight campsite is available for reservations <a href=http://www.recreation.gov/camping/Cottonwood_Group_Campsite/r/campgroundDetails.do?contractCode=NRSO&amp;parkId=75404&amp;topTabIndex=Search>here</a>.",
    "FacilityLatitude": 42.638333333333335,
    "FacilityTypeDescription": "Camping",
    "FacilityPhone": "307-886-5300",
    "FacilityDirections": "From Afton, Wyoming, take Highway 89 south approximately 7 miles to Smoot and watch for signs for the Cottonwood Lake Campground. <br /><br />The forest boundary is about a mile up the access road, and the campground is 6 miles beyond that. Continue past the west first loop of the campground, then go right at the Y intersection toward lake. The group picnic area is on the left side of the road.",
    "FacilityName": "COTTONWOOD GROUP PICNIC SITE",
    "LastUpdatedDate": "2015-03-12 02:42:19",
    "LegacyFacilityID": 75403,
    "OrgFacilityID": "AN375403",
    "FacilityID": 234518,
    "campsites": [
      {
        "LastUpdatedDate": "2015-03-12 03:12:41",
        "TypeOfUse": "Day",
        "CreatedDate": "2014-05-02 17:24:18",
        "CampsiteType": "GROUP PICNIC AREA",
        "CampsiteID": 11521,
        "CampsiteName": 1,
        "Loop": "COGPS",
        "CampsiteAccessible": false,
        "FacilityID": 234518,
        "attributes": [
          {
            "AttributeValue": "8:00 AM",
            "AttributeName": "Checkin Time"
          },
          {
            "AttributeValue": "10:00 PM",
            "AttributeName": "Checkout Time"
          },
          {
            "AttributeValue": "Pull-Through",
            "AttributeName": "Driveway Entry"
          },
          {
            "AttributeValue": "Gravel",
            "AttributeName": "Driveway Surface"
          },
          {
            "AttributeValue": 50,
            "AttributeName": "Max Num of People"
          },
          {
            "AttributeValue": 10,
            "AttributeName": "Max Num of Vehicles"
          },
          {
            "AttributeValue": 1,
            "AttributeName": "Min Num of People"
          },
          {
            "AttributeValue": "Domestic",
            "AttributeName": "Pets Allowed"
          },
          {
            "AttributeValue": "Y",
            "AttributeName": "Picnic Table"
          },
          {
            "AttributeValue": "Site-Specific",
            "AttributeName": "Site Reserve Type"
          },
          {
            "AttributeValue": "Single",
            "AttributeName": "Capacity/Size Rating"
          }
        ]
      }
    ],
    "address": {
      "FacilityAddressID": 8032546,
      "PostalCode": 83110,
      "AddressStateCode": "WY",
      "FacilityStreetAddress1": "671 North Washington",
      "City": "AFTON",
      "FacilityID": 234518,
      "AddressCountryCode": "USA"
    }
  }
}