{
  "type": "Feature",
  "geometry": {
    "type": "Point",
    "coordinates": [
      -110.81694444444445,
      42.64111111111111
    ]
  },
  "properties": {
    "FacilityLongitude": -110.81694444444445,
    "FacilityDescription": "<h2>Overview</h2>Cottonwood Group Campsite is located next to the scenic Cottonwood Lake on Salt River Pass in the lush forests of western Wyoming.<h4>Natural Features:</h4>Peaceful North Fork Creek flows through the campground. Its banks and the surrounding canyon are forested by dense stands of pines and aspens, which offer excellent shade and privacy. Vibrant summer wildflowers are abundant.<h4>Recreation:</h4>The lake offers great canoeing and boating for smaller craft and fishing for brook and cutthroat trout. <br /><br />Hiking, mountain biking and horseback riding trails are in the area.<h4>Facilities:</h4>This group campsite can accommodate up to 25 guests and is most appropriate for groups camping in tents. Two vehicles can be parked at the site (van-sized vehicles are the largest the site will accommodate) and six additional vehicles can be parked at the adjacent Cottonwood Lake Day Use Area. Single-family sites are available on a first-come, first-served basis. <br /><br />Vault toilets and drinking water are provided.",
    "FacilityLatitude": 42.64111111111111,
    "FacilityTypeDescription": "Camping",
    "FacilityPhone": "307-886-5300",
    "FacilityDirections": "From Afton, Wyoming, take Highway 89 south approximately 7 miles to Smoot. After a half-mile look for directional signs to Cottonwood Lake Campground.<br /><br />The Forest boundary is about one mile up the access road, and the campground is 6 miles beyond that. Continue past the first loop of the campground, then turn left at the Y intersection onto the east loop. The group site is at the far northern edge of this loop, just past the water pump.",
    "FacilityName": "COTTONWOOD GROUP CAMPSITE",
    "LastUpdatedDate": "2015-03-12 02:42:19",
    "LegacyFacilityID": 75404,
    "OrgFacilityID": "AN375404",
    "FacilityID": 234519,
    "campsites": [
      {
        "LastUpdatedDate": "2015-03-12 03:21:26",
        "TypeOfUse": "Overnight",
        "CreatedDate": "2014-05-02 17:30:49",
        "CampsiteType": "GROUP STANDARD NONELECTRIC",
        "CampsiteID": 19335,
        "CampsiteName": 1,
        "Loop": "COGC",
        "CampsiteAccessible": false,
        "FacilityID": 234519,
        "attributes": [
          {
            "AttributeValue": "Y",
            "AttributeName": "Campfire Allowed"
          },
          {
            "AttributeValue": "Single",
            "AttributeName": "Capacity/Size Rating"
          },
          {
            "AttributeValue": "2:00 PM",
            "AttributeName": "Checkin Time"
          },
          {
            "AttributeValue": "11:00 AM",
            "AttributeName": "Checkout Time"
          },
          {
            "AttributeValue": "Back-In",
            "AttributeName": "Driveway Entry"
          },
          {
            "AttributeValue": "Gravel",
            "AttributeName": "Driveway Surface"
          },
          {
            "AttributeValue": "Y",
            "AttributeName": "Fire Pit"
          },
          {
            "AttributeValue": 0,
            "AttributeName": "Hike In Distance to Site"
          },
          {
            "AttributeValue": "Y",
            "AttributeName": "Horse Stall/Corral"
          },
          {
            "AttributeValue": 25,
            "AttributeName": "Max Num of People"
          },
          {
            "AttributeValue": 2,
            "AttributeName": "Max Num of Vehicles"
          },
          {
            "AttributeValue": 1,
            "AttributeName": "Min Num of People"
          },
          {
            "AttributeValue": "Domestic",
            "AttributeName": "Pets Allowed"
          },
          {
            "AttributeValue": "Y",
            "AttributeName": "Picnic Table"
          },
          {
            "AttributeValue": "Full",
            "AttributeName": "Shade"
          },
          {
            "AttributeValue": "Site-Specific",
            "AttributeName": "Site Reserve Type"
          },
          {
            "AttributeValue": "Y",
            "AttributeName": "BBQ"
          }
        ]
      }
    ],
    "address": {
      "FacilityAddressID": 8032547,
      "PostalCode": 83110,
      "AddressStateCode": "WY",
      "FacilityStreetAddress1": "671 North Washington",
      "City": "AFTON",
      "FacilityID": 234519,
      "AddressCountryCode": "USA"
    }
  }
}