{
  "type": "Feature",
  "geometry": {
    "type": "Point",
    "coordinates": [
      -121.60888888888888,
      45.962500000000006
    ]
  },
  "properties": {
    "FacilityLongitude": -121.60888888888888,
    "FacilityDescription": "<h2>Overview</h2>Sitting just west of Washingtons second largest mountain, Mt. Adams, Atkisson Group Camp is open for campers between May and September and becomes a sno-park for a variety of activities in winter. The flat, forested terrain makes Atkisson a popular spot for hikers, mountain bikers and winter sports enthusiasts.<h4>Natural Features:</h4>Located in southwest Washington State, the Gifford Pinchot National Forest encompasses over 1.3 million acres, including the 110,000-acre Mount St. Helens National Volcanic Monument established by Congress in 1982. <br /><br />Atkisson is located in the Mount Adams Ranger District in the easternmost portion of the Gifford Pinchot National Forest. This Ranger District comprises 367,000 acres and includes Mt Adams Wilderness, Indian Heaven Wilderness and Trapper Creek Wilderness. <br /><br />Mt Adams, a potentially active stratovolcano and the second-tallest mountain in Washington state, is a prominent landmark of the District. Elevations here range between 1,200 feet at the Wind River Work Center (12 miles north of Carson, WA) and 12,276 feet at the summit of Mt. Adams.<br /><br /> The District also features a great diversity of habitats, from old growth to second growth forest, wetland areas, low and high elevation meadows and lakes, as well as glaciers.<h4>Recreation:</h4>The flat terrain surrounding Atkisson is ideal for biking and hiking during the warmer months. Huckleberry and mushroom picking is permitted, and Nordic skiing and and snowmobiling are popular during the winter. <h4>Facilities:</h4>This group site has two large paved areas with plenty of room for RVs. Atkisson will accommodate up to 50 people and offers 99 feet of paved driveway.<br /><br /> In winter, this area serves as Atkisson sno-park, with a covered warming shed a large wood burning stove.<br /><br />Campers must bring drinking water, but vault toilets, fire rings, grills and picnic tables are available.<h4>Nearby Attractions:</h4>Atkisson is a great base for exploring the region further, including the abundance of activities and sights around Mount Adams. The nearby town of Trout Lake offers restaurants and shopping.",
    "FacilityLatitude": 45.962500000000006,
    "FacilityTypeDescription": "Camping",
    "FacilityPhone": "541-338-7869",
    "FacilityDirections": "From I-5 at Vancouver, take Highway 14 east for 66 miles and continue on Highway 141 north for 15 miles to Forest Service Road 2400 (5 miles south of the town of Trout Lake). Turn northwest and head 3.5 miles to the Group Camp.",
    "FacilityName": "Atkisson Group camp",
    "LastUpdatedDate": "2015-03-12 02:15:42",
    "LegacyFacilityID": 71571,
    "OrgFacilityID": "AN371571",
    "FacilityID": 232797,
    "campsites": [
      {
        "LastUpdatedDate": "2015-03-05 04:21:21",
        "TypeOfUse": "Overnight",
        "CreatedDate": "2014-05-02 18:28:15",
        "CampsiteType": "GROUP STANDARD NONELECTRIC",
        "CampsiteID": 89745,
        "CampsiteName": 1,
        "Loop": "AREA ATKISSON",
        "CampsiteAccessible": false,
        "FacilityID": 232797,
        "attributes": [
          {
            "AttributeValue": "Single",
            "AttributeName": "Capacity/Size Rating"
          },
          {
            "AttributeValue": "4:00 PM",
            "AttributeName": "Checkin Time"
          },
          {
            "AttributeValue": "2:00 PM",
            "AttributeName": "Checkout Time"
          },
          {
            "AttributeValue": "Paved",
            "AttributeName": "Driveway Surface"
          },
          {
            "AttributeValue": "Y",
            "AttributeName": "Fire Pit"
          },
          {
            "AttributeValue": 50,
            "AttributeName": "Max Num of People"
          },
          {
            "AttributeValue": 20,
            "AttributeName": "Max Num of Vehicles"
          },
          {
            "AttributeValue": 1,
            "AttributeName": "Min Num of People"
          },
          {
            "AttributeValue": "Domestic",
            "AttributeName": "Pets Allowed"
          },
          {
            "AttributeValue": "Y",
            "AttributeName": "Picnic Table"
          },
          {
            "AttributeValue": "Site-Specific",
            "AttributeName": "Site Reserve Type"
          },
          {
            "AttributeValue": "Y",
            "AttributeName": "Campfire Allowed"
          }
        ]
      }
    ],
    "address": {
      "FacilityAddressID": 8030808,
      "PostalCode": 98610,
      "AddressStateCode": "WA",
      "FacilityStreetAddress1": "Gifford Pinchot NF Mt Adams Ranger District",
      "City": "CARSON",
      "FacilityID": 232797,
      "AddressCountryCode": "USA"
    }
  }
}