{
  "type": "Feature",
  "geometry": {
    "type": "Point",
    "coordinates": [
      -81.91583333333334,
      29.274166666666666
    ]
  },
  "properties": {
    "FacilityLongitude": -81.91583333333334,
    "FacilityDescription": "<h2>Overview</h2>Lake Shore Group Campground sits on the north shore of Fore Lake in Ocala National Forest. It is a favorite for scout, church and civic groups, as well as large families and reunions. <h4>Natural Features:</h4>Located in north central Florida, the Ocala National Forest spans four counties and 383,000 acres. It is the southernmost and oldest national forest east of the Mississippi River and protects the worlds largest contiguous sand pine scrub forest.<br><br>Lined by marshes, the 12-acre Fore Lake is home to many species of birds. The surrounding landscape is forested with saw palmetto and oak trees.<h4>Recreation:</h4>Fore Lake is an excellent spot for birding. Visitors can also picnic and fish along the shore. Campers who wish to venture out into the water can launch their electric-motor boats, canoes and kayaks from the facilitys boat ramp.<br><br>Swimming is allowed, but campers should be aware that there are alligators in this lake.<h4>Facilities:</h4>Lake Shore Group Camp is for tent camping, however RVs are allowed in the small parking area. The site can accommodate up to 50 guests and there are campsites in the shade and in the sun, all within sight of the lake. The centerpiece of the facility is the large accessible picnic shelter, perfect for group gatherings. A group grill, picnic tables and a restroom with showers and flush toilets are available.<br><br>The lake is situated in the historic community of Scrambletown, which has a store.<h4>Nearby Attractions:</h4>The Ocala National Forest is notable for its extensive off-road trail system catering to both ATV enthusiasts and Jeeps, as well as being a traditional destination for deer hunters. These opportunities are available within a short drive.",
    "FacilityLatitude": 29.274166666666666,
    "FacilityTypeDescription": "Camping",
    "FacilityPhone": "352-625-2520",
    "FacilityDirections": "From I-75, west of Ocala, take exit 352 onto State Route 40 east. Continue for 10 miles to County Road 314. Turn left on 314 and go 6 miles. Turn left onto 147th Avenue Road and look for the Lake Shore sign and entrance on left.",
    "FacilityName": "LAKE SHORE GROUP CAMP",
    "LastUpdatedDate": "2015-03-12 02:42:19",
    "LegacyFacilityID": 75399,
    "OrgFacilityID": "AN375399",
    "FacilityID": 234514,
    "campsites": [
      {
        "LastUpdatedDate": "2015-03-12 04:03:50",
        "TypeOfUse": "Overnight",
        "CreatedDate": "2014-05-02 17:50:45",
        "CampsiteType": "GROUP STANDARD NONELECTRIC",
        "CampsiteID": 43682,
        "CampsiteName": 1,
        "Loop": "LAKE SHORE GROUP CAMP",
        "CampsiteAccessible": false,
        "FacilityID": 234514,
        "attributes": [
          {
            "AttributeValue": "3:00 PM",
            "AttributeName": "Checkin Time"
          },
          {
            "AttributeValue": "1:00 PM",
            "AttributeName": "Checkout Time"
          },
          {
            "AttributeValue": "Gravel",
            "AttributeName": "Driveway Surface"
          },
          {
            "AttributeValue": 50,
            "AttributeName": "Max Num of People"
          },
          {
            "AttributeValue": 20,
            "AttributeName": "Max Num of Vehicles"
          },
          {
            "AttributeValue": 1,
            "AttributeName": "Min Num of People"
          },
          {
            "AttributeValue": "Full",
            "AttributeName": "Shade"
          },
          {
            "AttributeValue": "Site-Specific",
            "AttributeName": "Site Reserve Type"
          },
          {
            "AttributeValue": "Single",
            "AttributeName": "Capacity/Size Rating"
          }
        ]
      }
    ],
    "address": {
      "FacilityAddressID": 8032542,
      "PostalCode": 34488,
      "AddressStateCode": "FL",
      "FacilityStreetAddress1": "8442 N.E 147TH AVENUE ROAD",
      "City": "SILVER SPRINGS",
      "FacilityID": 234514,
      "AddressCountryCode": "USA"
    }
  }
}