{
  "type": "Feature",
  "geometry": {
    "type": "Point",
    "coordinates": [
      -86.54138888888889,
      36.323055555555555
    ]
  },
  "properties": {
    "FacilityLongitude": -86.54138888888889,
    "FacilityDescription": "<h2>Overview</h2>Avondale is a wonderful destination for recreationists looking a little boating on their day trip. Here, visitors can bring their family and friends for water sports and plenty of sunshine.<br /><br />The picnic area is on the shores of Old Hickory Lake, just a short drive from Nashville, Tennessee. The lake is named after Andrew Jackson, the 7th U.S. President and Tennessee native with the nickname &quot;Old Hickory.&quot;<h4>Natural Features:</h4>Old Hickory Lake is a reservoir in north-central Tennessee created by the Old Hickory Lock and Dam. The lake receives its primary inflow from the Cumberland River and spans 22,500 acres surrounded by wooded areas and grassy flatlands.<h4>Recreation:</h4>Avondale is an ideal launching point for boat fishing. Bank fishing is also popular, with  black bass, crappie and paddlefish in the area. Water skiing, sailing and swimming are also big attractions.<h4>Facilities:</h4>The group picnic shelter accommodates up to 50 people and 45 vehicles.Flush toilets and a boat ramp are available for use.<h4>Nearby Attractions:</h4>Hikers can take on the Old Hickory Lake Nature Trail, a 1.1 mile trail with three scenic loops. Mountain bikers of all skill levels can enjoy the Shutes Branch Mountain Biking Trail. <br /><br />The town of Hendersonville is very close and offers various historic districts to explore.",
    "FacilityLatitude": 36.323055555555555,
    "FacilityTypeDescription": "Camping",
    "FacilityPhone": "615-824-4989",
    "FacilityDirections": "N of Nashville on I-65,  exit at Vietnam Veterans Blvd E and follow ituntil it rejoins Gallatin Road (Highway 31E), turn right onto Shute Lanefrom Gallatin Road, turn right again onto Avondale Access Road.  Followsigns into recreation area.",
    "FacilityName": "AVONDALE",
    "LastUpdatedDate": "2015-03-12 02:10:59",
    "FacilityADAAccess": true,
    "LegacyFacilityID": 71015,
    "OrgFacilityID": "AN371015",
    "FacilityID": 232518,
    "campsites": [
      {
        "LastUpdatedDate": "2015-03-12 04:21:07",
        "TypeOfUse": "Day",
        "CreatedDate": "2014-05-02 17:53:11",
        "CampsiteType": "GROUP SHELTER ELECTRIC",
        "CampsiteID": 46024,
        "CampsiteName": 1,
        "Loop": "AVONDALE ",
        "CampsiteAccessible": true,
        "FacilityID": 232518,
        "attributes": [
          {
            "AttributeValue": "6:00 AM",
            "AttributeName": "Checkin Time"
          },
          {
            "AttributeValue": "10:00 PM",
            "AttributeName": "Checkout Time"
          },
          {
            "AttributeValue": "Paved",
            "AttributeName": "Driveway Surface"
          },
          {
            "AttributeValue": 20,
            "AttributeName": "Electricity Hookup"
          },
          {
            "AttributeValue": 50,
            "AttributeName": "Max Num of People"
          },
          {
            "AttributeValue": 45,
            "AttributeName": "Max Num of Vehicles"
          },
          {
            "AttributeValue": 1,
            "AttributeName": "Min Num of People"
          },
          {
            "AttributeValue": "Y",
            "AttributeName": "Picnic Table"
          },
          {
            "AttributeValue": "Partial",
            "AttributeName": "Shade"
          },
          {
            "AttributeValue": "Site-Specific",
            "AttributeName": "Site Reserve Type"
          },
          {
            "AttributeValue": "Y",
            "AttributeName": "Water Hookup"
          },
          {
            "AttributeValue": "Single",
            "AttributeName": "Capacity/Size Rating"
          }
        ]
      }
    ],
    "address": {
      "FacilityAddressID": 8030537,
      "PostalCode": 37066,
      "AddressStateCode": "TN",
      "FacilityStreetAddress1": "AVONDALE RECREATION",
      "City": "GALLATIN",
      "FacilityID": 232518,
      "AddressCountryCode": "USA"
    }
  }
}