{
  "type": "Feature",
  "geometry": {
    "type": "Point",
    "coordinates": [
      -114.48278055555556,
      44.99471944444444
    ]
  },
  "properties": {
    "FacilityLongitude": -114.48278055555556,
    "FacilityDescription": "<h2>Overview</h2>Yellowjacket Guard Station is a historic Forest Service Ranger Station and work center. Originally constructed in 1925 and remodeled in 1934 by the Civilian Conservation Corps, the structure is eligible for listing on the National Register of Historic Places. <h4>Natural Features:</h4>The guard station sits in the Yellowjacket Mountains within the Salmon-Challis National Forest in Idaho. The sizable front porch awards views of the scenic mountain meadow surrounding the station. A dense conifer forest covers the mountains and a few aspens dot the landscape. Beagle Creek flows nearby.<h4>Recreation:</h4>Hikers, horseback riders, mountain bikers and off-road enthusiasts will find many trails in the surrounding area. Hunting is also a popular activity. <a href=http://www.recreation.gov/marketing.do?goto=/safety.htm>Click here</a> for an Idaho OHV safety message.<br /><br />A 40-by-40 horse corral is located within the guard station complex.<h4>Facilities:</h4>The spacious guard station can sleep a maximum of four people in two bedrooms, with a double bed and one single bed. No linens or bedding are provided. The living room contains a couch, wood stove, table and chairs.  <br /><br />The small kitchen is equipped with a propane range and oven and sink, but no running water. Guests must bring their own drinking water, as well as dishes, utensils and cookware. <br /><br /> Other amenities include propane lights, a broom, axe, fire extinguisher and a shovel. A vault toilet is located outside.",
    "FacilityLatitude": 44.99471944444444,
    "FacilityTypeDescription": "Camping",
    "FacilityPhone": "208-756-5205",
    "FacilityDirections": "From Salmon, Idaho, take Highway 93 south 5 miles, to a right turn at Shoup Bridge onto Forest Road 021 and travel 44.5 miles to Cobalt Work Center facility on Panther Creek Road 055. Continue 8 miles south on Panther Creek Road, where you will come to Porphury Creek turnoff to the right, heading west. Continue approximately 11 miles along Porphury Creek Road/Forest Road 112 to Yellowjacket Guard Station.",
    "FacilityName": "YELLOWJACKET GUARD STATION",
    "LastUpdatedDate": "2015-03-12 02:39:10",
    "LegacyFacilityID": 75142,
    "OrgFacilityID": "AN375142",
    "FacilityID": 234286,
    "campsites": [
      {
        "LastUpdatedDate": "2015-03-12 03:31:39",
        "TypeOfUse": "Overnight",
        "CreatedDate": "2014-05-02 17:35:48",
        "CampsiteType": "CABIN NONELECTRIC",
        "CampsiteID": 25881,
        "CampsiteName": 1,
        "Loop": "YELLOWJACKET GUARD STATION ",
        "CampsiteAccessible": false,
        "FacilityID": 234286,
        "attributes": [
          {
            "AttributeValue": "11:00 AM",
            "AttributeName": "Checkout Time"
          },
          {
            "AttributeValue": 2,
            "AttributeName": "Max Num of People"
          },
          {
            "AttributeValue": 3,
            "AttributeName": "Max Num of Vehicles"
          },
          {
            "AttributeValue": 1,
            "AttributeName": "Min Num of People"
          },
          {
            "AttributeValue": "Domestic",
            "AttributeName": "Pets Allowed"
          },
          {
            "AttributeValue": "Site-Specific",
            "AttributeName": "Site Reserve Type"
          },
          {
            "AttributeValue": "2:00 PM",
            "AttributeName": "Checkin Time"
          }
        ]
      }
    ],
    "address": {
      "FacilityAddressID": 8032315,
      "PostalCode": 83467,
      "AddressStateCode": "ID",
      "FacilityStreetAddress1": "311 MCPHERSON ST",
      "City": "SALMON",
      "FacilityID": 234286,
      "AddressCountryCode": "USA"
    }
  }
}