{
  "type": "Feature",
  "geometry": {
    "type": "Point",
    "coordinates": [
      -114.72361111111111,
      44.36944444444445
    ]
  },
  "properties": {
    "FacilityLongitude": -114.72361111111111,
    "FacilityDescription": "<h2>Overview</h2>Bonanza CCC Group Campground is located nine miles up the scenic and historic Yankee Fork drainage. It is approximately 23 miles from Stanley, Idaho, at an elevation of 6,500 feet. <h4>Natural Features:</h4>Bonanza is situated in a beautiful valley near the Yankee Fork of the Salmon River. Lodgepole pines are scattered throughout the campground, providing limited shade. Summer wildflowers are abundant in the area.<h4>Recreation:</h4>The Yankee Fork provides good fishing for rainbow trout, cutthroat trout and whitefish.<br /><br />Many miles of trails crisscross the area, including the West Fork of Yankee Fork, Crimson Lake Trail and Lightning Creek Trail. Trailheads for each are not far from the campground.<h4>Facilities:</h4>The site is available for reservation from Memorial Day through Labor Day, and is for group camping only. Individual units are not reservable. <br /><br />The campground includes 13 camp spurs; each with a pad for parking vehicles and/or trailers, a picnic table and a campfire ring. The facility also offers a group area with two large fire rings, a grey water sink and several picnic tables. <br /><br />Camping spurs average from 45 to 50 feet deep. Five spurs are wide enough to accommodate one to two additional vehicles. The entire facility allows parking for approximately 40 vehicles without trailers and 20 vehicles with trailers. Please take this into consideration if your group brings trailers.<br /><br />Vault toilets, potable water, and trash collection are provided, but there is no electricity or other hookups.  Roads and parking spurs are gravel.<h4>Nearby Attractions:</h4>Yankee Fork has a rich history, all of which is easily accessed from the campground. Within a mile is the ghost town of Bonanza and two miles further is the ghost town of Custer. Bonanza, Boot Hill and Custer cemeteries are in the vicinity.<br /><br />The Yankee Fork Gold Dredge towers over the stream near Custer. Interpretive tours of the structure are offered for a fee from Memorial Day weekend through Labor Day. <br /><br />Sunbeam Dam site is nine miles down the canyon. Information about the only dam ever built on the Salmon River are provided at the rivers edge.",
    "FacilityLatitude": 44.36944444444445,
    "FacilityTypeDescription": "Camping",
    "FacilityPhone": "208-879-4100",
    "FacilityDirections": "From Highway 75, turn onto Yankee Fork Road (Forest Road 013) at Sunbeam Dam overlook. Travel approximately seven miles north on Yankee Fork Road and turn left at the Bonanza Guard Station. Continue for approximately half a mile to the campground.",
    "FacilityName": "BONANZA CCC GROUP CAMPGROUND",
    "LastUpdatedDate": "2015-03-12 02:39:10",
    "LegacyFacilityID": 75129,
    "OrgFacilityID": "AN375129",
    "FacilityID": 234275,
    "campsites": [
      {
        "LastUpdatedDate": "2015-03-12 04:45:11",
        "TypeOfUse": "Overnight",
        "CreatedDate": "2014-05-02 18:16:03",
        "CampsiteType": "GROUP STANDARD NONELECTRIC",
        "CampsiteID": 74275,
        "CampsiteName": 1,
        "Loop": "BONANZA CCC GROUP CAMPGROUND ",
        "CampsiteAccessible": false,
        "FacilityID": 234275,
        "attributes": [
          {
            "AttributeValue": "Single",
            "AttributeName": "Capacity/Size Rating"
          },
          {
            "AttributeValue": "2:00 PM",
            "AttributeName": "Checkin Time"
          },
          {
            "AttributeValue": "12:00 PM",
            "AttributeName": "Checkout Time"
          },
          {
            "AttributeValue": "Y",
            "AttributeName": "Fire Pit"
          },
          {
            "AttributeValue": 70,
            "AttributeName": "Max Num of People"
          },
          {
            "AttributeValue": 20,
            "AttributeName": "Max Num of Vehicles"
          },
          {
            "AttributeValue": 1,
            "AttributeName": "Min Num of People"
          },
          {
            "AttributeValue": "Y",
            "AttributeName": "Picnic Table"
          },
          {
            "AttributeValue": "Site-Specific",
            "AttributeName": "Site Reserve Type"
          },
          {
            "AttributeValue": "Y",
            "AttributeName": "Campfire Allowed"
          }
        ]
      }
    ],
    "address": {
      "FacilityAddressID": 8032305,
      "PostalCode": 83226,
      "AddressStateCode": "ID",
      "FacilityStreetAddress1": "HC 63, BOX 1669",
      "City": "CHALLIS",
      "FacilityID": 234275,
      "AddressCountryCode": "USA"
    }
  }
}