{
  "type": "Feature",
  "geometry": {
    "type": "Point",
    "coordinates": [
      -115.53194444444445,
      45.72666666666667
    ]
  },
  "properties": {
    "FacilityLongitude": -115.53194444444445,
    "FacilityDescription": "<h2>Overview</h2>Walker Cabin is nestled among aspen trees just off Crooked River Road #233, which leads into the Gospel-Hump Wilderness Area, in the Nez Perce National Forest.<br /><br /> The cabin was originally built around 1930 as a summer home. Jerry and Helen Walker purchased the cabin in 1967, then donated it to the U.S. Forest Service in the 1980s. It is now available for public recreational use.<br /><br /> <h4>Natural Features:</h4>Walker Cabin sits at an elevation of 4,500 feet near the northern part of Gospel-Hump Wilderness, an area that is moist and densely forested. Big game species likeelk, mule and whitetail deer, black bear, cougar, moose, mountain goat and mountain sheep live within the Wilderness. Chukar, grouse, squirrels and songbirds make their home here as well.  <h4>Recreation:</h4>Crooked River is a popular area for many recreational opportunities, including hiking, trout fishing, hunting, snowmobiling and cross-country skiing. A nice hiking trailis located behind the cabin.<br /><br /> Nearby trails lead to the Orogrande Summit, Buffalo Hump and Gospel Hump. Snowshoes may be required on the trails in winter. There are several lakes within a 3-mile radius that are easily accessible by foot or off-road vehicle. <h4>Facilities:</h4>The rustic cabin has two bedrooms with two single beds each, a living room with a wood insert in the fireplace, several chairs, a table, a broomand a kitchen with a wood cook stove. A vault toilet is located in a separate building. Guests can find firewood in a shed behind the cabin.<br /><br />  Running water and electricity are not available. Guests should bring their own water supply and garbage bags to pack out their trash. Cookware, kitchen utensils, bedding and blankets are not provided. A lantern or flashlight and extra batteries are recommended (<a href=http://www.fs.usda.gov/Internet/FSE_DOCUMENTS/fsm91_057164.pdf>click here for more details about this cabin</a>).<h4>Nearby Attractions:</h4>The cabin is less than a mile from Orogrande, a historic mining site that is now a ghost town. The closest town, Elk City, Idaho, is a remote community with limited facilities that include a grocery store, restaurant, bar, laundromat, convenience store and gas stations.",
    "FacilityLatitude": 45.72666666666667,
    "FacilityTypeDescription": "Camping",
    "FacilityPhone": "208-842-2245",
    "FacilityDirections": "From State Highway 14, turn south on Crooked River Road #233 and proceed approximately 8 miles to the cabin on the right.",
    "FacilityName": "WALKER CABIN",
    "LastUpdatedDate": "2015-03-12 02:41:32",
    "LegacyFacilityID": 75312,
    "OrgFacilityID": "AN375312",
    "FacilityID": 234445,
    "campsites": [
      {
        "LastUpdatedDate": "2015-03-05 04:41:14",
        "TypeOfUse": "Overnight",
        "CreatedDate": "2014-05-02 18:07:58",
        "CampsiteType": "CABIN NONELECTRIC",
        "CampsiteID": 64898,
        "CampsiteName": 1,
        "Loop": "AREA WALKER CABIN",
        "CampsiteAccessible": false,
        "FacilityID": 234445,
        "attributes": [
          {
            "AttributeValue": "12:00 PM",
            "AttributeName": "Checkin Time"
          },
          {
            "AttributeValue": "12:00 PM",
            "AttributeName": "Checkout Time"
          },
          {
            "AttributeValue": "Gravel",
            "AttributeName": "Driveway Surface"
          },
          {
            "AttributeValue": 4,
            "AttributeName": "Max Num of People"
          },
          {
            "AttributeValue": 0,
            "AttributeName": "Max Num of Vehicles"
          },
          {
            "AttributeValue": 1,
            "AttributeName": "Min Num of People"
          },
          {
            "AttributeValue": "Site-Specific",
            "AttributeName": "Site Reserve Type"
          },
          {
            "AttributeValue": "Y",
            "AttributeName": "Cabin Heating"
          }
        ]
      }
    ],
    "address": {
      "FacilityAddressID": 8032474,
      "PostalCode": 83525,
      "AddressStateCode": "ID",
      "FacilityStreetAddress1": "416 USFS DRIVE",
      "City": "ELK CITY",
      "FacilityID": 234445,
      "AddressCountryCode": "USA"
    }
  }
}