{
  "type": "Feature",
  "geometry": {
    "type": "Point",
    "coordinates": [
      -105.73305555555555,
      32.958333333333336
    ]
  },
  "properties": {
    "FacilityLongitude": -105.73305555555555,
    "FacilityDescription": "<h2>Overview</h2>Upper Fir Group Area is one of the most popular campsites in the Sacramento Mountain area.  Unique to its neighboring campgrounds, its set far back from public roads, allowing for true peace and quiet. <p>The campground is on the northwestern portion of the Lincoln National Forest, a protected area spanning an incredible 1.1 million acres of land. Spend your days exploring the mountains, or head west for a day trip to explore White Sands National Monument, the worlds largest dune field of pure, white gypsum sand.</p><h4>Natural Features:</h4>Set 9,000 feet above sea level in the Sacramento Mountains, Upper Fir Group Area is close to breathtaking scenic overlooks, spanning the far-reaching desert valley of the Tularosa Basin. The high-elevation region offers a mixture of pine, fir, aspen, and oak trees, with high mountain meadows full of wildflowers and blossoming plants. <h4>Recreation:</h4>An open meadow, perfect for sports like ultimate Frisbee or horseshoes, is connected to the campground. The Rim Trail is a short hike or drive away, offering epic views, rocky inclines, and switchbacks for adventurous mountain bikers, hikers, and horse-back riders. Further down, the same trail opens up to motorcyclists as well. <h4>Facilities:</h4>This is one of the only group sites with water access. Upper Fir comfortably fits groups as large as 120, and its connected to Lower Fir Group if your party has a need for an additional group of up to 70 campers. <h4>Nearby Attractions:</h4>The campground is a mile from the town of Cloudcroft, a quaint tourist village with New Mexicos only standing railroad trestle.",
    "FacilityLatitude": 32.958333333333336,
    "FacilityTypeDescription": "Camping",
    "FacilityPhone": "575-682-7570",
    "FacilityDirections": "From Alamogordo, take US 82 east 17 miles through Cloudcroft. Turn leftonto NM 244 towards Ruidoso and go 1/2 mile. Upper Fir Group Area is onForest Road 422 at the end of the road.",
    "FacilityName": "UPPER FIR GROUP AREA",
    "LastUpdatedDate": "2015-03-12 02:01:15",
    "LegacyFacilityID": 70071,
    "OrgFacilityID": "AN370071",
    "FacilityID": 231889,
    "campsites": [
      {
        "LastUpdatedDate": "2015-03-12 04:43:29",
        "TypeOfUse": "Overnight",
        "CreatedDate": "2014-05-02 18:15:10",
        "CampsiteType": "GROUP STANDARD AREA NONELECTRIC",
        "CampsiteID": 73052,
        "CampsiteName": 1,
        "Loop": "GPUP",
        "CampsiteAccessible": false,
        "FacilityID": 231889,
        "attributes": [
          {
            "AttributeValue": "12:00 PM",
            "AttributeName": "Checkin Time"
          },
          {
            "AttributeValue": "11:00 AM",
            "AttributeName": "Checkout Time"
          },
          {
            "AttributeValue": "Basic",
            "AttributeName": "Condition Rating"
          },
          {
            "AttributeValue": "Back-In",
            "AttributeName": "Driveway Entry"
          },
          {
            "AttributeValue": "Gravel",
            "AttributeName": "Driveway Surface"
          },
          {
            "AttributeValue": 120,
            "AttributeName": "Max Num of People"
          },
          {
            "AttributeValue": 35,
            "AttributeName": "Max Num of Vehicles"
          },
          {
            "AttributeValue": 1,
            "AttributeName": "Min Num of People"
          },
          {
            "AttributeValue": "Site-Specific",
            "AttributeName": "Site Reserve Type"
          },
          {
            "AttributeValue": "Single",
            "AttributeName": "Capacity/Size Rating"
          }
        ]
      }
    ],
    "address": {
      "FacilityAddressID": 8029907,
      "PostalCode": 88317,
      "AddressStateCode": "NM",
      "FacilityStreetAddress1": "PO BOX 836",
      "City": "CLOUDCROFT",
      "FacilityID": 231889,
      "AddressCountryCode": "USA"
    }
  }
}