{
  "type": "Feature",
  "geometry": {
    "type": "Point",
    "coordinates": [
      -88.62222222222222,
      39.55138888888889
    ]
  },
  "properties": {
    "FacilityLongitude": -88.62222222222222,
    "FacilityDescription": "<h2>Overview</h2>Bo Wood Day Use Area sits on the northern shore of Lake Shelbyville in the heart of central Illinois. <br /><br />The lake and surrounding land offer outdoor activities for people of all ages, including fishing, swimming, picnicking and simply relaxing.<h4>Natural Features:</h4>This facility is partially forested and offers a combination of shade and sun. Oak and hickory are the dominant tree species in the lake region. <br /><br />Foliage turns a variety of red, orange, purple and yellow each fall, while prairie flowers dot the landscape in spring and summer. <br /><br />Numerous species of songbirds, shorebirds, waterfowl and raptors inhabit the lake area, as do mammals such as cottontail rabbit, white-tail deer, gray and fox squirrel, muskrat and mink.<h4>Recreation:</h4>Bo Wood Day Use Area is a fun place to relax along the lake. There is plenty of open space in which children can play. <br /><br />Boaters have access to a multi-lane boat ramp and courtesy dock, and Lake Shelbyville offers a multitude of fishing opportunities for catfish, crappie, largemouth bass, muskie, walleye, white bass and bluegill. For those without a boat, several managed ponds with farmed fish are available around the lake. <br /><br />Hunting areas within a short drive offer numerous game species, including quail, rabbit, pheasant, deer, dove, turkey, waterfowl and woodcock.<h4>Facilities:</h4>This facility offers one reservable group picnic shelter that can accommodate up to 50 people. Six picnic tables, a large grill, flush toilets and electric hookups are provided.<h4>Nearby Attractions:</h4>Wolf Creek State Park, Woods Lake Waterfowl Refuge and Okaw Bluff Wetlands Complex are popular locations for wildlife watching, birding and hunting near Lake Shelbyville.",
    "FacilityLatitude": 39.55138888888889,
    "FacilityTypeDescription": "Camping",
    "FacilityPhone": "217-774-3951",
    "FacilityDirections": "From Sullivan, Illinois, take State Route 32 south for 2 miles to the Forrest W. Bo Wood sign, then turn right and drive one mile to the day use area.",
    "FacilityName": "FORREST W. BO WOOD (DAY USE)",
    "LastUpdatedDate": "2015-03-12 02:30:29",
    "LegacyFacilityID": 73607,
    "OrgFacilityID": "AN373607",
    "FacilityID": 233752,
    "campsites": [
      {
        "LastUpdatedDate": "2015-03-12 03:52:34",
        "TypeOfUse": "Day",
        "CreatedDate": "2014-05-02 17:39:08",
        "CampsiteType": "GROUP PICNIC AREA",
        "CampsiteID": 29582,
        "CampsiteName": "PS1",
        "Loop": "Forrest W Bo Wood Day Use",
        "CampsiteAccessible": false,
        "FacilityID": 233752,
        "attributes": [
          {
            "AttributeValue": "8:00 AM",
            "AttributeName": "Checkin Time"
          },
          {
            "AttributeValue": "10:00 PM",
            "AttributeName": "Checkout Time"
          },
          {
            "AttributeValue": 20,
            "AttributeName": "Electricity Hookup"
          },
          {
            "AttributeValue": 50,
            "AttributeName": "Max Num of People"
          },
          {
            "AttributeValue": 15,
            "AttributeName": "Max Num of Vehicles"
          },
          {
            "AttributeValue": 1,
            "AttributeName": "Min Num of People"
          },
          {
            "AttributeValue": "Domestic",
            "AttributeName": "Pets Allowed"
          },
          {
            "AttributeValue": "Partial",
            "AttributeName": "Shade"
          },
          {
            "AttributeValue": "Site-Specific",
            "AttributeName": "Site Reserve Type"
          },
          {
            "AttributeValue": "Single",
            "AttributeName": "Capacity/Size Rating"
          }
        ]
      }
    ],
    "address": {
      "FacilityAddressID": 8031773,
      "PostalCode": 62565,
      "AddressStateCode": "IL",
      "FacilityStreetAddress1": "1989 State Hwy 16 ",
      "City": "SHELBYVILLE",
      "FacilityID": 233752,
      "AddressCountryCode": "USA"
    }
  }
}