{
  "type": "Feature",
  "geometry": {
    "type": "Point",
    "coordinates": [
      -90.26888888888888,
      45.846944444444446
    ]
  },
  "properties": {
    "FacilityLongitude": -90.26888888888888,
    "FacilityDescription": "<h2>Overview</h2>Sailor Lake Pavilion is part of rustic Sailor Lake Campground, both adjacent to scenic Sailor Lake. Its secluded setting makes it a popular location for family and group events. <br /><br />The pavilion is adjacent to the campground and the scenic lake, which is popular for fishing. Nearby off-road vehicle trails are also quite the draw.<h4>Natural Features:</h4>The pavilion is situated on the northwestern shore of Sailor Lake at an elevation of about 1,460 feet. The area is shaded by a mixed hardwood forest.<h4>Recreation:</h4>Sailor Lake Pavilion provides access to the 60-mile Flambeau Trail System. The trail is highlighted by rolling terrain, tree-lined corridors, wooden bridges and vistas overlooking various bogs and lakes. It is a popular snowmobiling location during winter months.<br /><br />The picnic area is adjacent to 170-acre Sailor Lake, which is popular for boating and fishing. Anglers will find healthy populations of pan fish and northern pike. A boat ramp is located a mile south of the adjacent campground.<h4>Facilities:</h4>The pavilion is a day-use picnic area that can accommodate groups of up to 30 people. No overnight camping is available at the site. The pavilion is equipped with multiple tables, grills and a campfire circle. Vault toilets and drinking water are provided.<h4>Nearby Attractions:</h4>Sailor Lake is located approximately 11 miles southeast of Fifield. The city boasts a variety of tourist attractions, including historic sites, a reconstructed logging dam and a couple of war memorials.",
    "FacilityLatitude": 45.846944444444446,
    "FacilityTypeDescription": "Camping",
    "FacilityPhone": "715-762-2461",
    "FacilityDirections": "From the intersection of Highways 13 and 70 in Fifield, drive about 8 miles east on Highway 70 to Forest Road 139. Turn right (south) and continue on Forest Road 139 about 3 miles to the Sailor Lake Boat Landing and Picnic Area, just past the campground road.",
    "FacilityName": "SAILOR LAKE PAVILION",
    "LastUpdatedDate": "2015-03-12 02:32:49",
    "LegacyFacilityID": 73857,
    "OrgFacilityID": "AN373857",
    "FacilityID": 233924,
    "campsites": [
      {
        "LastUpdatedDate": "2015-03-12 04:48:35",
        "TypeOfUse": "Day",
        "CreatedDate": "2014-05-02 18:11:07",
        "CampsiteType": "GROUP SHELTER NONELECTRIC",
        "CampsiteID": 68100,
        "CampsiteName": 1,
        "Loop": "SAILOR LAKE PAVILION ",
        "CampsiteAccessible": false,
        "FacilityID": 233924,
        "attributes": [
          {
            "AttributeValue": "6:00 AM",
            "AttributeName": "Checkin Time"
          },
          {
            "AttributeValue": "10:00 PM",
            "AttributeName": "Checkout Time"
          },
          {
            "AttributeValue": "Gravel",
            "AttributeName": "Driveway Surface"
          },
          {
            "AttributeValue": 30,
            "AttributeName": "Max Num of People"
          },
          {
            "AttributeValue": 15,
            "AttributeName": "Max Num of Vehicles"
          },
          {
            "AttributeValue": 1,
            "AttributeName": "Min Num of People"
          },
          {
            "AttributeValue": "Y",
            "AttributeName": "Picnic Table"
          },
          {
            "AttributeValue": "Full",
            "AttributeName": "Shade"
          },
          {
            "AttributeValue": "Site-Specific",
            "AttributeName": "Site Reserve Type"
          },
          {
            "AttributeValue": "Single",
            "AttributeName": "Capacity/Size Rating"
          }
        ]
      }
    ],
    "address": {
      "FacilityAddressID": 8031945,
      "PostalCode": 54552,
      "AddressStateCode": "WI",
      "FacilityStreetAddress1": "1170 4TH AVE. SOUTH",
      "City": "PARK FALLS",
      "FacilityID": 233924,
      "AddressCountryCode": "USA"
    }
  }
}