{
  "type": "Feature",
  "geometry": {
    "type": "Point",
    "coordinates": [
      -90.78388888888888,
      36.91916666666666
    ]
  },
  "properties": {
    "FacilityLongitude": -90.78388888888888,
    "FacilityDescription": "<h2>Overview</h2>Pinewoods Lake Recreation Area sits next to Pinewoods Lake in southeastern Missouri. It is an ideal location to enjoy lake fishing and scenic trails.<h4>Natural Features:</h4>The lake is located on the southeastern quadrant of the Mark Twain National Forest. The area is densely wooded.<h4>Recreation:</h4>A 1.3-mile walking trail surrounds the lake. Most of the trail has a concrete surface and is accessible. The entire trail is relatively flat, with no difficult sections. Circling the 32-acre lake, the trail provides views of the lake, songbirds and wildlife, and an abundance of wildflowers.<br /><br />The lake offers a floating fishing pier and a concrete boat ramp. Anglers can enjoy fishing for bass, sunfish and catfish.<h4>Facilities:</h4>The day-use picnic shelter can accommodate up to 75 people. It is equipped with tables and large grills. Accessible vault toilets are provided. Trash collection service is not available; visitors must carry out all garbage.<h4>Nearby Attractions:</h4>Ellsinore is the closest city to the campground, just 3 miles away, with a few dining options, a grocery store and fuel station.",
    "FacilityLatitude": 36.91916666666666,
    "FacilityTypeDescription": "Camping",
    "FacilityDirections": "From Poplar Bluff, Missouri, go 7 miles north on U.S. Highway 67, then travel 16 miles east on U.S. Highway 60.",
    "FacilityName": "PINEWOODS LAKE REC AREA",
    "LastUpdatedDate": "2015-03-12 02:09:23",
    "FacilityADAAccess": true,
    "LegacyFacilityID": 70829,
    "OrgFacilityID": "AN370829",
    "FacilityID": 232420,
    "campsites": [
      {
        "LastUpdatedDate": "2015-03-12 04:36:37",
        "TypeOfUse": "Day",
        "CreatedDate": "2014-05-02 17:59:55",
        "CampsiteType": "GROUP PICNIC AREA",
        "CampsiteID": 54277,
        "CampsiteName": 1,
        "Loop": "PINE",
        "CampsiteAccessible": true,
        "FacilityID": 232420,
        "attributes": [
          {
            "AttributeValue": "9:00 AM",
            "AttributeName": "Checkin Time"
          },
          {
            "AttributeValue": "9:00 PM",
            "AttributeName": "Checkout Time"
          },
          {
            "AttributeValue": "Paved",
            "AttributeName": "Driveway Surface"
          },
          {
            "AttributeValue": 75,
            "AttributeName": "Max Num of People"
          },
          {
            "AttributeValue": 20,
            "AttributeName": "Max Num of Vehicles"
          },
          {
            "AttributeValue": 10,
            "AttributeName": "Min Num of People"
          },
          {
            "AttributeValue": "Domestic",
            "AttributeName": "Pets Allowed"
          },
          {
            "AttributeValue": "Lakefront",
            "AttributeName": "Proximity to Water"
          },
          {
            "AttributeValue": "Full",
            "AttributeName": "Shade"
          },
          {
            "AttributeValue": "Site-Specific",
            "AttributeName": "Site Reserve Type"
          },
          {
            "AttributeValue": "Single",
            "AttributeName": "Capacity/Size Rating"
          }
        ]
      }
    ],
    "address": {
      "FacilityAddressID": 8030438,
      "PostalCode": 63902,
      "AddressStateCode": "MO",
      "FacilityStreetAddress1": "1420 MAUD ST",
      "City": "POPLAR BLUFF",
      "FacilityID": 232420,
      "AddressCountryCode": "USA"
    }
  }
}