{
  "type": "Feature",
  "geometry": {
    "type": "Point",
    "coordinates": [
      -105.93166666666667,
      39.34
    ]
  },
  "properties": {
    "FacilityLongitude": -105.93166666666667,
    "FacilityDescription": "<h2>Overview</h2>Roberts Cabin is one of the recognized historic cabins in Pike &amp; San Isabel National Forests. The primitive cabin dates back to the mining and railroad era of the 1880s, and is eligible for placement in the National Register of Historic Places. <br /><br />Through the ages, the structure has been used as a residence, a blacksmiths shop and stables. In 1993, the piece of history was restored to its original form and converted for use as a cabin rental. <h4>Natural Features:</h4>Roberts Cabin is located in the South Park Ranger District, which inludes South Park, part of the Mosquito Range, Eleven Mile Canyon, Jefferson Lake Recreation Areas, the Tarryall Mountains and Puma Hills.<br /><br />The cabin offers expansive views of the Front Range and is located at the base of the Boreas Pass, a 11,492 foot high mountain pass in central Colorado.  <br /><br />Wildlife sightings may include elk, deer, black bear, golden eagles and the great horned owl.  <h4>Recreation:</h4>Bird and wildlife watching are popular pastimes. In summer, many hiking trails are available to explore, this includes the extensive Colorado Trail that extends across the state from Denver to Durango. <br /><br />Winter recreation like cross country skiing and sledding are available, but the cabin is closed in peak winter months from December to April. <h4>Facilities:</h4>This is a remote, two-story log cabin, with one room on each floor and a steep staircase leading up to the top floor. Up to eight guests may sleep here; bedding includes two double beds, two single beds and a sleeper sofa. Lanterns and a wood stove are provided, and a vault toilet is outside. Parking can accommodate up to four vehicles.  <br /><br />No water is available and no cooking utensils are available either. Guests are advised to bring plenty of water for drinking, cooking and cleaning. They should also bring cooking pots and utensils, sleeping bags or blankets, flashlights, matches, outdoor furniture and firewood. <h4>Nearby Attractions:</h4>The cabin is convenient to Como, a town steeped with railroad history. It is also near Breckenridge and the Colorado Trail.",
    "FacilityLatitude": 39.34,
    "FacilityTypeDescription": "Camping",
    "FacilityDirections": "From Denver, Colorado, take Highway 285 southwest about 75 miles to thetown of Como. Turn north on County Road 33 and go approximately 4 milesto the cabin. Parking is along east side of the road.<br /><br />Guests must have combination lock to cabin prior to arrival.",
    "FacilityName": "ROBERTS CABIN",
    "LastUpdatedDate": "2015-03-12 02:31:17",
    "LegacyFacilityID": 73704,
    "OrgFacilityID": "AN373704",
    "FacilityID": 233808,
    "campsites": [
      {
        "LastUpdatedDate": "2015-03-12 03:19:37",
        "TypeOfUse": "Overnight",
        "CreatedDate": "2014-05-02 17:30:01",
        "CampsiteType": "CABIN NONELECTRIC",
        "CampsiteID": 18852,
        "CampsiteName": "CABIN",
        "Loop": "ROBERTS CABIN ",
        "CampsiteAccessible": false,
        "FacilityID": 233808,
        "attributes": [
          {
            "AttributeValue": "2:00 PM",
            "AttributeName": "Checkin Time"
          },
          {
            "AttributeValue": "12:00 PM",
            "AttributeName": "Checkout Time"
          },
          {
            "AttributeValue": "Gravel",
            "AttributeName": "Driveway Surface"
          },
          {
            "AttributeValue": 8,
            "AttributeName": "Max Num of People"
          },
          {
            "AttributeValue": 4,
            "AttributeName": "Max Num of Vehicles"
          },
          {
            "AttributeValue": 1,
            "AttributeName": "Min Num of People"
          },
          {
            "AttributeValue": "Site-Specific",
            "AttributeName": "Site Reserve Type"
          },
          {
            "AttributeValue": "Y",
            "AttributeName": "Cabin Heating"
          }
        ]
      }
    ],
    "address": {
      "FacilityAddressID": 8031829,
      "PostalCode": 80440,
      "AddressStateCode": "CO",
      "FacilityStreetAddress1": "PO BOX 219",
      "City": "FAIRPLAY",
      "FacilityID": 233808,
      "AddressCountryCode": "USA"
    }
  }
}