{
  "type": "Feature",
  "geometry": {
    "type": "Point",
    "coordinates": [
      -108.12527777777777,
      38.33277777777778
    ]
  },
  "properties": {
    "FacilityLongitude": -108.12527777777777,
    "FacilityDescription": "<h2>Overview</h2>The historic Silesca Cabin, once used as a ranger station, is a semi-rustic dwelling with comfortable modern conveniences like electricity, a shower and refrigerator. Located 40 minutes southwest of the city of Montrose, the cabin is set back 100 feet from the main road, providing easy access with some privacy. <br /><br />The cabin is accessible in the summer and fall by passenger vehicle, when the road is dry. Four-wheel drive vehicles are recommended when the road is wet.<h4>Natural Features:</h4>The cabin is perched in a meadow surrounded by spruce and aspen trees at an elevation of 9,200 feet. The meadow is along the Uncompahgre Plateau, bordered on the east by the wide valleys of the Gunnison and Uncompahgre Rivers, and on the west by the narrow gorges of the Dolores and San Miguel Rivers. <h4>Recreation:</h4>Hiking, mountain biking, off-road vehicle riding, horseback riding, hunting and wildlife viewing are all available in the vicinity. Silesca Pond is a short walk north of the cabin. <h4>Facilities:</h4>The rustic cabin accommodates up to six guests. Electricity and non-potable running water are included and a small barn is available for short-term storage of off-road vehicles, bicycles and similar equipment.   <br /><br />Amenities include three bedrooms with six twin beds, a bathroom with a shower and flush toilet, an electric stove, refrigerator and a wood stove. Limited cooking utensils, dishes and cleaning supplies are provided. A campfire ring and picnic table are located outside. <br /><br />No drinking water is available. Items to bring include food, bedding, warm clothing, toilet paper, flashlights, towels, dish soap and toiletries.  <a href=http://www.fs.usda.gov/recarea/gmug/recreation/camping-cabins/recarea/?recid=32844&amp;actid=101>Click here</a> for more cabin details.",
    "FacilityLatitude": 38.33277777777778,
    "FacilityTypeDescription": "Camping",
    "FacilityPhone": "(970) 240-5300",
    "FacilityDirections": "Follow Highway 90 southwest from Montrose. Watch for signs as the highway makes several turns as it weaves its way out of town. The pavement ends where the road begins to climb out of the Uncompahgre River Valley and enters lands administered by the Bureau of Land Management. In 20 miles, it enters the Uncompahgre National Forest. Silesca Cabin is about a half-mile further on the left side of the road.",
    "FacilityName": "SILESCA CABIN",
    "LastUpdatedDate": "2015-03-12 02:45:27",
    "LegacyFacilityID": 93668,
    "OrgFacilityID": "AN393668",
    "FacilityID": 234667,
    "campsites": [
      {
        "LastUpdatedDate": "2015-03-05 04:46:24",
        "TypeOfUse": "Overnight",
        "CreatedDate": "2014-05-02 18:18:32",
        "CampsiteType": "CABIN ELECTRIC",
        "CampsiteID": 77042,
        "CampsiteName": "Silesca Cabin",
        "Loop": "SILESCA CABIN",
        "CampsiteAccessible": false,
        "FacilityID": 234667,
        "attributes": [
          {
            "AttributeValue": "Y",
            "AttributeName": "Fire Pit"
          },
          {
            "AttributeValue": "Y",
            "AttributeName": "Food Locker"
          },
          {
            "AttributeValue": 6,
            "AttributeName": "Max Num of People"
          },
          {
            "AttributeValue": 4,
            "AttributeName": "Max Num of Vehicles"
          },
          {
            "AttributeValue": 1,
            "AttributeName": "Min Num of People"
          },
          {
            "AttributeValue": "Y",
            "AttributeName": "Picnic Table"
          },
          {
            "AttributeValue": "Partial",
            "AttributeName": "Shade"
          },
          {
            "AttributeValue": "Drive-In",
            "AttributeName": "Site Access"
          },
          {
            "AttributeValue": "Site-Specific",
            "AttributeName": "Site Reserve Type"
          },
          {
            "AttributeValue": 30,
            "AttributeName": "Electricity Hookup"
          }
        ]
      }
    ],
    "address": {
      "FacilityAddressID": 8032706,
      "PostalCode": 81401,
      "AddressStateCode": "CO",
      "FacilityStreetAddress1": "2505 South Townsend Avenue",
      "City": "Montrose",
      "FacilityID": 234667,
      "AddressCountryCode": "USA"
    }
  }
}