{
  "type": "Feature",
  "geometry": {
    "type": "Point",
    "coordinates": [
      -111.72194444444445,
      38.549166666666665
    ]
  },
  "properties": {
    "FacilityLongitude": -111.72194444444445,
    "FacilityDescription": "<h2>Overview</h2>Twin Creeks Picnic Area is is a day-use site located next to Fish Lake, Twin Creeks and the Fishlake Scenic Byway at an elevation of 8,800 feet. Visitors enjoy fishing, boating and exploring local trails.<h4>Natural Features:</h4>The shelter sits amid scattered pines and aspens on the shore above Fish Lake. Sagebrush and summer wildflowers dot the landscape.<h4>Recreation:</h4>Fish Lake is Utahs largest natural mountain lake, covering 2,500 acres. It is famous for its 20-40 pound Mackinaw lake trout. Anglers also enjoy fishing for rainbow trout and splake. Boating, canoeing, swimming and scuba diving are popular activities.<br><br>The 5-mile Pelican Canyon Trail begins a mile away at Bowery Creek Campground. It leads through meadows and dense forests of spruce, pine and aspen as it climbs to the 11,633-foot Fish Lake Hightop. <br><br>The popular Lakeshore National Recreation Trail extends around the eastern side of the lake. Hikers are rewarded with stunning lake views after climbing 900 feet in elevation.<h4>Facilities:</h4>Twin Creeks contains one accessible group picnic site that can accommodate up to 100 people. A large shelter with lake views is on-site, covering several picnic tables, grills and a campfire ring. An amphitheater is located across the parking area. <br><br>Flush toilets and drinking water are provided. The large parking area and short trail to the shelter are paved.<br><br>Three resorts are located in the Fish Lake Basin, offering camping and fishing supplies, RV parks with hookups, cabin and boat rentals, marinas, gas, restaurants, groceries, laundry facilities and showers. The resorts are open from Memorial Day to Labor Day.<h4>Nearby Attractions:</h4>Johnson Valley Reservoir is just north of Fish Lake, offering additional fishing and boating opportunities.",
    "FacilityLatitude": 38.549166666666665,
    "FacilityTypeDescription": "Camping",
    "FacilityDirections": "From Highway 24 northwest of Loa, Utah, take Highway 25 northeast approximately 9 miles to the campground.",
    "FacilityName": "TWIN CREEKS PICNIC",
    "LastUpdatedDate": "2015-03-12 02:01:15",
    "FacilityADAAccess": true,
    "LegacyFacilityID": 70110,
    "OrgFacilityID": "AN370110",
    "FacilityID": 231922,
    "campsites": [
      {
        "LastUpdatedDate": "2015-03-12 04:12:27",
        "TypeOfUse": "Day",
        "CreatedDate": "2014-05-02 17:48:17",
        "CampsiteType": "GROUP PICNIC AREA",
        "CampsiteID": 40246,
        "CampsiteName": 1,
        "Loop": "TWIN",
        "CampsiteAccessible": true,
        "FacilityID": 231922,
        "attributes": [
          {
            "AttributeValue": "Single",
            "AttributeName": "Capacity/Size Rating"
          },
          {
            "AttributeValue": "8:00 AM",
            "AttributeName": "Checkin Time"
          },
          {
            "AttributeValue": "10:00 PM",
            "AttributeName": "Checkout Time"
          },
          {
            "AttributeValue": "Paved",
            "AttributeName": "Driveway Surface"
          },
          {
            "AttributeValue": "Y",
            "AttributeName": "Fire Pit"
          },
          {
            "AttributeValue": 100,
            "AttributeName": "Max Num of People"
          },
          {
            "AttributeValue": 30,
            "AttributeName": "Max Num of Vehicles"
          },
          {
            "AttributeValue": 1,
            "AttributeName": "Min Num of People"
          },
          {
            "AttributeValue": "Y",
            "AttributeName": "Picnic Table"
          },
          {
            "AttributeValue": "Full",
            "AttributeName": "Shade"
          },
          {
            "AttributeValue": "Site-Specific",
            "AttributeName": "Site Reserve Type"
          },
          {
            "AttributeValue": "Y",
            "AttributeName": "Campfire Allowed"
          }
        ]
      }
    ],
    "address": {
      "FacilityAddressID": 8029940,
      "PostalCode": 847747,
      "AddressStateCode": "UT",
      "FacilityStreetAddress1": "138 South Main",
      "City": "Loa",
      "FacilityID": 231922,
      "AddressCountryCode": "USA"
    }
  }
}