{
  "type": "Feature",
  "geometry": {
    "type": "Point",
    "coordinates": [
      -111.17500000000001,
      39.57361111111111
    ]
  },
  "properties": {
    "FacilityLongitude": -111.17500000000001,
    "FacilityDescription": "<h2>Overview</h2>South Hughes Group Campground is located in beautiful Huntington Canyon, along the Huntington Canyon National Scenic Byway on Utah Highway 31. It sits at an elevation of approximately 8,000 feet. Many recreational activities are available, including hiking, biking and fishing.<h4>Natural Features:</h4>Large spruce trees cover the campground, offering plentiful shade. Grassy meadows and thick stands of aspens surround the site. Huntington Creek flows just across the road from the campground.<h4>Recreation:</h4>Popular activities include fishing, hunting, hiking, mountain biking, horseback riding, rock climbing and scenic driving. Huntington Creek is a Blue Ribbon fishery, offering high quality fishing for brown, cutthroat and rainbow trout.<br /><br />The 4-mile Left Fork of the Huntington National Recreation Trail is nearby and open to hikers and horseback riders. The 10-mile Fish Creek Trail, for hiking, biking and horseback riding, is also close by.<h4>Facilities:</h4>The campground contains one group site that can accommodate up to 100 people. One accessible vault toilet is provided, but there is no water, electricity or garbage service. The large parking area within the campground is dirt. Grassy areas provide nice spots for tents. <br /><br />Beyond the group site are several individual walk-to tent sites available on a first-come, first-served basis. <h4>Nearby Attractions:</h4>The Huntington Canyon National Scenic Byway is part of the 86-mile Energy Loop. It offers stunning mountain and lake views as it tops 10,000 feet in elevation.<br /><br />The historic Stuart Guard Station Visitor Center is nearby, offering a glimpse of the 1930s life of a ranger and his family who once lived there. Exhibits of Civilian Conservation Corps projects and original equipment are also on display. Area information is available there as well.",
    "FacilityLatitude": 39.57361111111111,
    "FacilityTypeDescription": "Camping",
    "FacilityPhone": "435-384-2372",
    "FacilityDirections": "The campground is located about 26 miles west of Huntington, Utah, along Highway 31. Turn east at the sign for South Hughes Canyon.",
    "FacilityName": "SOUTH HUGHES GROUP",
    "LastUpdatedDate": "2015-03-12 02:31:17",
    "FacilityADAAccess": true,
    "LegacyFacilityID": 73664,
    "OrgFacilityID": "AN373664",
    "FacilityID": 233799,
    "campsites": [
      {
        "LastUpdatedDate": "2015-03-12 04:46:53",
        "TypeOfUse": "Overnight",
        "CreatedDate": "2014-05-02 18:16:54",
        "CampsiteType": "GROUP STANDARD NONELECTRIC",
        "CampsiteID": 75485,
        "CampsiteName": "SOUTHH",
        "Loop": "SOUTH HUGHES GROUP ",
        "CampsiteAccessible": true,
        "FacilityID": 233799,
        "attributes": [
          {
            "AttributeValue": "2:00 PM",
            "AttributeName": "Checkin Time"
          },
          {
            "AttributeValue": "1:00 PM",
            "AttributeName": "Checkout Time"
          },
          {
            "AttributeValue": "Basic",
            "AttributeName": "Condition Rating"
          },
          {
            "AttributeValue": "Back-In",
            "AttributeName": "Driveway Entry"
          },
          {
            "AttributeValue": "Gravel",
            "AttributeName": "Driveway Surface"
          },
          {
            "AttributeValue": 100,
            "AttributeName": "Max Num of People"
          },
          {
            "AttributeValue": 40,
            "AttributeName": "Max Num of Vehicles"
          },
          {
            "AttributeValue": 1,
            "AttributeName": "Min Num of People"
          },
          {
            "AttributeValue": "Full",
            "AttributeName": "Shade"
          },
          {
            "AttributeValue": "Site-Specific",
            "AttributeName": "Site Reserve Type"
          },
          {
            "AttributeValue": "Single",
            "AttributeName": "Capacity/Size Rating"
          }
        ]
      }
    ],
    "address": {
      "FacilityAddressID": 8031820,
      "PostalCode": 84501,
      "AddressStateCode": "UT",
      "FacilityStreetAddress1": "599 W. PRICE RIVER DR.",
      "City": "PRICE",
      "FacilityID": 233799,
      "AddressCountryCode": "USA"
    }
  }
}