{
  "type": "Feature",
  "geometry": {
    "type": "Point",
    "coordinates": [
      -110.33611111111111,
      40.54194444444444
    ]
  },
  "properties": {
    "FacilityLongitude": -110.33611111111111,
    "FacilityDescription": "<h2>Overview</h2>Yellowstone Group Campground lies along its pretty namesake river on the southern slope of the Uinta Mountains, about 40 miles from Duchesne, Utah. Visitors come to the area to enjoy its extensive off-road trail system and great fishing opportunities.<h4>Natural Features:</h4>The campground sits on the banks of the Yellowstone River at an elevation of 7700 feet. A forest of aspen, maple and Ponderosa pine covers the area. Wildlife and summer wildflowers are abundant.<h4>Recreation:</h4>The Yellowstone River offers fishing for rainbow, brown, brook and cutthroat trout.<br><br>The Yellowstone ATV Trail System is conveniently close, with over 50 miles of trail on the Petty Mountain and Dry Gulch Loops. Hiking and biking are also allowed on these trails.<h4>Facilities:</h4>The campground contains one group site with picnic tables and campfire rings. Eighty people and eight vehicles can be accommodated. Vault toilets, drinking water and trash collection are provided. Roads and parking spurs are gravel. Several first come, first served single sites are available as well.<h4>Nearby Attractions:</h4>Yellowstone Canyon offers beautiful mountain scenery, additional first come, first served campgrounds, a small reservoir and trailheads with access to the High Uintas Wilderness.<br><br>Hiking, backpacking and horseback riding are popular in the wilderness area and numerous sparkling lakes provide great backcountry fishing opportunities.",
    "FacilityLatitude": 40.54194444444444,
    "FacilityTypeDescription": "Camping",
    "FacilityPhone": "435-722-5018",
    "FacilityDirections": "From Duchesne, Utah: Take Highway 87 north to Mountain Home, then travel on Uinta and Ouray Indian Reservation Road to Forest Road 131 to Forest Road 119. FR 119 is rough and rocky in places.",
    "FacilityName": "YELLOWSTONE GROUP CAMPGROUND",
    "LastUpdatedDate": "2015-03-12 02:31:17",
    "LegacyFacilityID": 73716,
    "OrgFacilityID": "AN373716",
    "FacilityID": 233816,
    "campsites": [
      {
        "LastUpdatedDate": "2015-03-12 04:17:37",
        "TypeOfUse": "Overnight",
        "CreatedDate": "2014-05-02 17:57:27",
        "CampsiteType": "GROUP STANDARD NONELECTRIC",
        "CampsiteID": 51458,
        "CampsiteName": "GROUP",
        "Loop": "YELLOWSTONE GROUP CAMPGROUND ",
        "CampsiteAccessible": false,
        "FacilityID": 233816,
        "attributes": [
          {
            "AttributeValue": "Single",
            "AttributeName": "Capacity/Size Rating"
          },
          {
            "AttributeValue": "2:00 PM",
            "AttributeName": "Checkin Time"
          },
          {
            "AttributeValue": "1:00 PM",
            "AttributeName": "Checkout Time"
          },
          {
            "AttributeValue": "Back-In",
            "AttributeName": "Driveway Entry"
          },
          {
            "AttributeValue": "Gravel",
            "AttributeName": "Driveway Surface"
          },
          {
            "AttributeValue": "Y",
            "AttributeName": "Fire Pit"
          },
          {
            "AttributeValue": 80,
            "AttributeName": "Max Num of People"
          },
          {
            "AttributeValue": 8,
            "AttributeName": "Max Num of Vehicles"
          },
          {
            "AttributeValue": 1,
            "AttributeName": "Min Num of People"
          },
          {
            "AttributeValue": "Y",
            "AttributeName": "Picnic Table"
          },
          {
            "AttributeValue": "Full",
            "AttributeName": "Shade"
          },
          {
            "AttributeValue": "Site-Specific",
            "AttributeName": "Site Reserve Type"
          },
          {
            "AttributeValue": "Y",
            "AttributeName": "Campfire Allowed"
          }
        ]
      }
    ],
    "address": {
      "FacilityAddressID": 8031837,
      "PostalCode": 84066,
      "AddressStateCode": "UT",
      "FacilityStreetAddress1": "650 W HWY 40 PO BOX 127",
      "City": "ROOSEVELT",
      "FacilityID": 233816,
      "AddressCountryCode": "USA"
    }
  }
}