{
  "type": "Feature",
  "geometry": {
    "type": "Point",
    "coordinates": [
      -130.64444444444445,
      55.094166666666666
    ]
  },
  "properties": {
    "FacilityLongitude": -130.64444444444445,
    "FacilityDescription": "<h2>Overview</h2>Hugh Smith Lake Cabin is located on the mainland within the Misty Fiords National Monument Wilderness. This rustic, secluded retreat is open year-round for relaxation and recreation in Alaskas beautiful Inside Passage.<br /><br /> The site can be accessed by float plane, depending on conditions. Guests are responsible for their own travel arrangements and safety, and must bring several of their own amenities.<h4>Natural Features:</h4>The cabin sits on a peninsula that extends into Hugh Smith Lake. It is surrounded by an old-growth forest of Sitka spruce, western hemlock and cedar. Guests have views of the lake and the gentle, forested slopes on the opposite shore.<br /><br />This area is home to a large population of brown bears. Other species that make their home in the wilderness include Sitka black-tailed deer, wolves, martens and moose. A variety of waterfowl may be seen around the lake. <h4>Recreation:</h4>There is a working fish weir near the outlet of the lake. Anglers can fish for cutthroat, Dolly Varden and sockeye salmon. Guests can use the cabins 14-foot aluminum skiff with oars, but they must provide their own life jackets.<br /><br />An abandoned cannery site sits at the east end of the lake, inviting exploration. Hikers will find a trail leading to saltwater.<h4>Facilities:</h4>This 12x14-ft. <a href=http://www.fs.fed.us/r10/tongass/cabins/cabin_layouts.shtml>pan-abode style</a> cabin sleeps six and comes equipped with two single bunks, two double bunks, a table and benches, wood stove, firewood, axe and splitting maul, broom and an outhouse.<br /><br /> Water and electricity are not provided. Water is available from the lake, but guests should be sure to treat water before drinking or cooking with it. It is recommended that guests bring their own water supply.<br /><br />Other items to pack include sleeping bags, sleeping pads, lanterns or flashlights, cookware, plates, utensils, food, toilet paper, garbage bags, a fire extinguisher and fire starter. Guests are expected to pack out trash and clean the cabin before leaving. <a href=http://www.fs.usda.gov/recarea/tongass/recreation/camping-cabins/recarea/?recid=78887&amp;actid=101 target=_blank>Click here</a> for more cabin details.",
    "FacilityLatitude": 55.094166666666666,
    "FacilityTypeDescription": "Camping",
    "FacilityDirections": "The cabin is located approximately 55 air miles southeast of Ketchikan on the mainland south of Marten Arm. Accessible by floatplane. No moorage available. This cabin is in a designated Wilderness area, and access by helicopter is illegal. Refer to USGS Ketchikan A-3.<br /><br />In fall, winter and early spring, the cabin may be inaccessible due to frozen lake surface (floatplanes cannot land). Please contact the Ketchikan-Misty Fiords Ranger District at (907) 225-2148 for information prior to making reservations during these periods.",
    "FacilityName": "HUGH SMITH LAKE CABIN",
    "LastUpdatedDate": "2015-03-12 02:18:02",
    "LegacyFacilityID": 71793,
    "OrgFacilityID": "AN371793",
    "FacilityID": 232971,
    "campsites": [
      {
        "LastUpdatedDate": "2015-03-05 04:10:01",
        "TypeOfUse": "Overnight",
        "CreatedDate": "2014-05-02 18:09:33",
        "CampsiteType": "CABIN NONELECTRIC",
        "CampsiteID": 66964,
        "CampsiteName": "M07",
        "Loop": "AREA HUGH SMITH LAKE CABIN",
        "CampsiteAccessible": false,
        "FacilityID": 232971,
        "attributes": [
          {
            "AttributeValue": "12:00 PM",
            "AttributeName": "Checkin Time"
          },
          {
            "AttributeValue": "12:00 PM",
            "AttributeName": "Checkout Time"
          },
          {
            "AttributeValue": 6,
            "AttributeName": "Max Num of People"
          },
          {
            "AttributeValue": 0,
            "AttributeName": "Max Num of Vehicles"
          },
          {
            "AttributeValue": 1,
            "AttributeName": "Min Num of People"
          },
          {
            "AttributeValue": "Site-Specific",
            "AttributeName": "Site Reserve Type"
          },
          {
            "AttributeValue": "Y",
            "AttributeName": "Cabin Heating"
          }
        ]
      }
    ],
    "address": {
      "FacilityAddressID": 8030982,
      "AddressStateCode": "AK",
      "City": "KETCHIKAN/MISTY",
      "FacilityID": 232971,
      "AddressCountryCode": "USA"
    }
  }
}