{
  "type": "Feature",
  "geometry": {
    "type": "Point",
    "coordinates": [
      -138.50277777777777,
      59.248333333333335
    ]
  },
  "properties": {
    "FacilityLongitude": -138.50277777777777,
    "FacilityDescription": "<h2>Overview</h2>Tanis Mesa South Cabin is located in a duplex with Tanis Mesa North Cabin. The cabin is tucked between Tanis Mesa and the Brabazon Mountain Range, offeringyear-round relaxation and recreation.<br /><br />The site can be accessed by wheeled plane, depending on conditions. An airstrip is adjacent to the cabin. Visitors are responsible for their own travel arrangements and safety, and must bring several of their own amenities.<h4>Natural Features:</h4>The cabin sits on mostly flat terrain surrounded by blueberry bushes. Interspersed stands of cottonwood, alder and willow begin about half a mile from the cabin.<br /><br /> Visitors can enjoy views of Tanis Mesa, which sits half a mile to the west. Tanis Mesa is a unique geologic feature that stands about 500 feet above the cabin. The peaks of the Brabazon Range are a mile to the east, with elevations of over 3,000 feet.<br /><br /> Wildlife in the Brabazon Mountain Range includes moose, brown bear and mountain goats. <h4>Recreation:</h4>Tanis Lake is 2 miles north of the cabin and can be hiked to relatively easily except for the last quarter mile, which is dense brush. Hikers are rewarded with views of Fassett Glacier cascading into the lakes northeast end.<br /><br />The Brabazon Mountains offer opportunities for excellent mountain goat hunting. Moose and brown bear hunting is good around the cabin. <h4>Facilities:</h4>This is the south half of a 14x40-ft. <a href=http://www.fs.fed.us/r10/tongass/cabins/cabin_layouts.shtml>A-frame style</a>cabin. It sleeps five people and comes equipped with four single bunks and a sleeping loft. The cabin also has a table and benches, oil heater, broom, picnic table, fire ring and outhouse. A 12x12-ft. meat shed is located outside, which is shared with Tanis Mesa North Cabin.<br /><br /> Water, heating oil and electricity are not provided. Visitors must supply #1 diesel oil the heater, as well as their own drinking water. Other items to bring include sleeping bags, sleeping pads, food, a cooking stove, cookware, plates, utensils, lanterns or flashlights, toilet paper, garbage bags, a fire extinguisher and fire starter. Visitors are expected to pack out trash and clean the cabin before leaving. <a href=http://www.fs.usda.gov/recarea/tongass/recreation/camping-cabins/recarea/?recid=79231&amp;actid=101 target=_blank>Click here</a> for more cabin details.",
    "FacilityLatitude": 59.248333333333335,
    "FacilityTypeDescription": "Camping",
    "FacilityDirections": "The cabin is located 50 miles southeast of Yakutat between Tanis Mesa and Brabazon Mountain Range. Access is by wheeled plane only via an 1,800-ft. airstrip at the cabin.",
    "FacilityName": "TANIS MESA SOUTH CABIN",
    "LastUpdatedDate": "2015-03-12 02:20:23",
    "LegacyFacilityID": 71923,
    "OrgFacilityID": "AN371923",
    "FacilityID": 233092,
    "campsites": [
      {
        "LastUpdatedDate": "2015-03-05 04:31:18",
        "TypeOfUse": "Overnight",
        "CreatedDate": "2014-05-02 18:26:38",
        "CampsiteType": "CABIN NONELECTRIC",
        "CampsiteID": 87957,
        "CampsiteName": "Y06S",
        "Loop": "AREA TANIS MESA SOUTH CABIN",
        "CampsiteAccessible": false,
        "FacilityID": 233092,
        "attributes": [
          {
            "AttributeValue": "12:00 PM",
            "AttributeName": "Checkin Time"
          },
          {
            "AttributeValue": "12:00 PM",
            "AttributeName": "Checkout Time"
          },
          {
            "AttributeValue": 5,
            "AttributeName": "Max Num of People"
          },
          {
            "AttributeValue": 0,
            "AttributeName": "Max Num of Vehicles"
          },
          {
            "AttributeValue": 1,
            "AttributeName": "Min Num of People"
          },
          {
            "AttributeValue": "Site-Specific",
            "AttributeName": "Site Reserve Type"
          },
          {
            "AttributeValue": "Y",
            "AttributeName": "Cabin Heating"
          }
        ]
      }
    ],
    "address": {
      "FacilityAddressID": 8031103,
      "AddressStateCode": "AK",
      "City": "CHATAM/YAKUTAT",
      "FacilityID": 233092,
      "AddressCountryCode": "USA"
    }
  }
}