{
  "type": "Feature",
  "geometry": {
    "type": "Point",
    "coordinates": [
      -139.08583333333334,
      59.29722222222222
    ]
  },
  "properties": {
    "FacilityLongitude": -139.08583333333334,
    "FacilityDescription": "<h2>Overview</h2>Italio River Cabin is situated on the west bank of Hooligan Creek about half a mile from the Old Italio River and the Gulf of Alaska. This remote retreat is open year-round and makes an ideal base for fishing or hunting trips.<br /><br /> The site can be accessed by wheeled plane, depending on conditions. The nearby airstrip is on tidal flats, making it prone to flooding and debris. Visitors are responsible for their own travel arrangements and safety, and must bring several of their own amenities.<h4>Natural Features:</h4>The cabin sits on relatively flat terrain that can get very wet. The surrounding vegetation is predominantly brush with scattered willow and alder thickets and cottonwoods. The nearby tidal flats often flood during high tide or heavy rains (<a href=http://tidesandcurrents.noaa.gov/tide_predictions.shtml?gid=276>local tide charts</a>).<br /><br />Large populations of moose and brown bears live in this area. Bald eagles and ravens are common, and gulls are often seen along the river.<h4>Recreation:</h4>The Old Italio, New Italio and Akwe River systems offer outstanding fishing for rainbow trout, Dolly Varden and steelhead, as well as sockeye, pink, king and silver salmon. Moose hunting is good to excellent.<h4>Facilities:</h4>This 14x20-ft. <a href=http://www.fs.fed.us/r10/tongass/cabins/cabin_layouts.shtml>A-frame style</a> cabin sleeps six people and comes with two single bunks and a sleeping loft. Other amenities include a table with benches, broom and an oil heater.<br /><br />A picnic table and campfire ring are located outside. An outhouse with pit toilet and a 12x12-ft. meat shed are located on-site.<br /><br />Water, electricity and heating oil are not provided. Visitors must bring their own supply of drinking water, as well as #1 stove oil for the heater. One gallon lasts 2-10 hours, depending on the heat setting. An empty 5-gallon tank is provided.<br /><br />Other items to bring include sleeping bags, sleeping pads, food, a cooking stove, cookware, plates, utensils, lanterns or flashlights, toilet paper, garbage bags, a fire extinguisher and fire starter. Visitors are expected to pack out trash and clean the cabin before leaving. <a href=http://www.fs.usda.gov/recarea/tongass/recreation/camping-cabins/recarea/?recid=79165&amp;actid=101 target=_blank>Click here</a> for more cabin details.",
    "FacilityLatitude": 59.29722222222222,
    "FacilityTypeDescription": "Camping",
    "FacilityDirections": "Located 30 miles SE of Yakutat, the cabin is on the west bank of Hooligan Creek, a half-mile from the Old Italio River. Access is by wheeled plane on a tidal flat airstrip. The 1,600x100-ft. airstrip may flood at extreme high tides or after heavy rains. Please consult tide charts in advance, since tides can affectaccess to this cabin.",
    "FacilityName": "ITALIO RIVER CABIN",
    "LastUpdatedDate": "2015-03-12 02:20:23",
    "LegacyFacilityID": 71926,
    "OrgFacilityID": "AN371926",
    "FacilityID": 233095,
    "campsites": [
      {
        "LastUpdatedDate": "2015-03-05 04:11:35",
        "TypeOfUse": "Overnight",
        "CreatedDate": "2014-05-02 18:10:20",
        "CampsiteType": "CABIN NONELECTRIC",
        "CampsiteID": 67998,
        "CampsiteName": "Y11",
        "Loop": "AREA ITALIO RIVER CABIN",
        "CampsiteAccessible": false,
        "FacilityID": 233095,
        "attributes": [
          {
            "AttributeValue": "12:00 PM",
            "AttributeName": "Checkin Time"
          },
          {
            "AttributeValue": "12:00 PM",
            "AttributeName": "Checkout Time"
          },
          {
            "AttributeValue": 6,
            "AttributeName": "Max Num of People"
          },
          {
            "AttributeValue": 0,
            "AttributeName": "Max Num of Vehicles"
          },
          {
            "AttributeValue": 1,
            "AttributeName": "Min Num of People"
          },
          {
            "AttributeValue": "Site-Specific",
            "AttributeName": "Site Reserve Type"
          },
          {
            "AttributeValue": "Y",
            "AttributeName": "Cabin Heating"
          }
        ]
      }
    ],
    "address": {
      "FacilityAddressID": 8031106,
      "PostalCode": 99689,
      "AddressStateCode": "AK",
      "FacilityStreetAddress1": "P.O. BOX 327",
      "City": "TONGASS/YAKUTAT",
      "FacilityID": 233095,
      "AddressCountryCode": "USA"
    }
  }
}