{
  "type": "Feature",
  "geometry": {
    "type": "Point",
    "coordinates": [
      -79.53416666666666,
      37.575833333333335
    ]
  },
  "properties": {
    "FacilityLongitude": -79.53416666666666,
    "FacilityDescription": "<h2>Overview</h2>Cave Mountain Lake Group Picnic Shelter is nestled in the Blue Ridge Mountains of Virginia, and welcomes visitors to enjoy the rustic beauty and peacefulness of the area. Easy access from the interstate, close proximity to historic Lexington and access to Natural Bridge make Cave Mountain Lake an ideal destination.<h4>Natural Features:</h4>Cave Mountain Lake covers seven acres and was built in the 1930s by the Civilian Conservation Corps, using existing natural rock buttresses to form a 35-foot dam. A grassy field extends from the lakes sandy beach and hills lush with hardwood and conifer trees paint a scenic backdrop.<h4>Recreation:</h4>The lake offers refreshing opportunities to splash and swim on a designated sandy swim beach. Anglers fish from the waters edge outside the beach area. Boating is not allowed, so beyond of the swimming area, the lake offers plentiful photography, birding and wildlife viewing opportunities.<br /><br />Hiking trails surround the area, offering everything from a short walk around the lake to an all-day hike along the nearby ridges. Backpackers enjoy the Appalachian National Scenic Trail and the James River Face and the Thunder Ridge Wilderness areas.<h4>Facilities:</h4>The picnic shelter is a historic structure that does not support accessibility standards. Parking is available in the day-use parking area and the shelter is reached via a foot bridge along a gravel path. <br /><br />The shelter can accommodate up to 50 people. Amenities include electricity for small appliances, a fireplace, eight picnic tables, a double pedestal grill, trash cans and a drinking fountain with a spigot. Flush toilets and showers are available at the beach bathhouse.<h4>Nearby Attractions:</h4>Lexington, Virginia, just 20 minutes away, is home to the gravesites of Stonewall Jackson and Robert E. Lee. Its a charming town with conveniences like grocery stores and gas stations. Ice and other sundries can be found at small stores along State Route 759.",
    "FacilityLatitude": 37.575833333333335,
    "FacilityTypeDescription": "Camping",
    "FacilityPhone": "540-291-2188",
    "FacilityDirections": "From I- 81 North, take Exit 175 just south of Natural Bridge, Virginia. Go north on U.S. Highway 11 toward Natural Bridge (left turn facing the Exxon station). From Natural Bridge, follow Route 130 East at the intersection with U.S. Highway 11 (right turn at the Natural Bridge parking lot). Continue on Route 130 East for approximately 4 miles to Natural Bridge Station. Turn right onto State Route 759 and continue for approximately 3 miles. Turn right onto State Route 781. The entrance for Cave Mountain Lake Recreation Area is approximately 1.6 miles ahead. Turn left into the recreation area and continue to the beach area parking. The group picnic shelter is across the foot bridge to the right of the main path to the lake.",
    "FacilityName": "CAVE MOUNTAIN LAKE GROUP PICNIC SHELTER",
    "LastUpdatedDate": "2015-03-12 02:22:00",
    "LegacyFacilityID": 72108,
    "OrgFacilityID": "AN372108",
    "FacilityID": 233205,
    "campsites": [
      {
        "LastUpdatedDate": "2015-03-05 04:51:11",
        "TypeOfUse": "Day",
        "CreatedDate": "2014-05-02 18:20:10",
        "CampsiteType": "GROUP PICNIC AREA",
        "CampsiteID": 79549,
        "CampsiteName": "G1",
        "Loop": "CAVE MOUNTAIN LAKE GROUP PICNIC SHELTER",
        "CampsiteAccessible": false,
        "FacilityID": 233205,
        "attributes": [
          {
            "AttributeValue": "0:00 AM",
            "AttributeName": "Checkout Time"
          },
          {
            "AttributeValue": "Gravel",
            "AttributeName": "Driveway Surface"
          },
          {
            "AttributeValue": 50,
            "AttributeName": "Max Num of People"
          },
          {
            "AttributeValue": 10,
            "AttributeName": "Min Num of People"
          },
          {
            "AttributeValue": 1,
            "AttributeName": "Min Num of Vehicles"
          },
          {
            "AttributeValue": "Full",
            "AttributeName": "Shade"
          },
          {
            "AttributeValue": "Site-Specific",
            "AttributeName": "Site Reserve Type"
          },
          {
            "AttributeValue": "0:00 AM",
            "AttributeName": "Checkin Time"
          }
        ]
      }
    ],
    "address": {
      "FacilityAddressID": 8031214,
      "PostalCode": 24579,
      "AddressStateCode": "VA",
      "FacilityStreetAddress1": "811 Cave Mountain Lake Road",
      "City": "Natural Bridge Station",
      "FacilityID": 233205,
      "AddressCountryCode": "USA"
    }
  }
}